Workbook

Sheet LEIA-ME
A1: SANDLAND / PLANO DE IMPLEMENTAÇÃO
A4: Modelo de trabalho | B4: Uma pessoa responsável + agentes de IA; WIP principal recomendado = 1.
A5: Cadência | B5: Sprints por aceite, sem duração fixa. Não converter 72 sprints em 144 semanas.
A6: Horizonte | B6: v1.0 completa; v1.1 maturação; v1.2/v2.0 evoluções propostas com ADRs explícitas.
A7: Escala do plano | B7: 72 sprints; 720 tarefas; 72 gates; 19 versões; 37 requisitos; 18 ADRs.
A8: Estado inicial | B8: Planejamento. Nenhuma implementação, benchmark ou homologação do app foi realizada nesta entrega.
A9: Como começar | B9: Abra Tarefas, filtre Sprint = S01 e siga SL-S01-01. Feche o gate somente com evidência e revisão humana.
A10: Colunas editáveis | B10: Status, Responsável, Revisor humano, Data de aceite, Evidência obtida, ADR/justificativa e Observações.
A11: Fechamento | B11: OK exige Concluído + revisor + data + evidência + dependências fechadas. PREENCHER CAMPOS NÃO PROVA A EVIDÊNCIA.
A12: Dispensas | B12: Somente itens condicionais podem usar Dispensado (ADR), com justificativa/evidência/revisão. Invariantes essenciais não são dispensáveis.
A13: Fórmulas | B13: Recalculadas ao abrir em Excel/LibreOffice. Previews podem não calcular fórmulas. Use o status inicial como planejado, não como progresso certificado.
A14: Dependências | B14: IDs no nível de tarefa/gate. Ordem numérica é rota solo recomendada; dependências técnicas de sprints estão na aba Sprints.
A15: Artefatos | B15: Caminhos listados são saídas futuras no repositório do app. Evidência exigida não significa evidência já produzida.
... A23: Base | B23: RFC do autor e Sandland-RFC-Integracao-e-Desconstrucao.md, preservados sem alteração.

Sheet Painel
A1: SANDLAND / VISÃO DO ROADMAP
A4: Sprints planejados | E4: 72
A5: Tarefas detalhadas | E5: 720
A6: Gates humanos | E6: 72
A7: Versões/marcos | E7: 19
A8: Requisitos rastreados | E8: 37
A9: ADRs a decidir | E9: 18
A10: Tarefas com fechamento válido | E10: =COUNTIFS(Tarefas!$G$2:$G$793,"<>Gate",Tarefas!$X$2:$X$793,"OK")
A11: Gates com fechamento válido | E11: =COUNTIFS(Tarefas!$G$2:$G$793,"Gate",Tarefas!$X$2:$X$793,"OK")
A12: Itens que exigem revisão | E12: =COUNTIF(Tarefas!$X$2:$X$793,"REVISAR")
A14: Estado de entrega: plano, não implementação. Todos os itens começam Não iniciado. Contagem de tarefas não mede horas, semanas ou dificuldade. Fórmulas exigem recálculo no editor de planilhas e não validam a veracidade das evidências.
A18: Abrir Tarefas
A19: Abrir Sprints
A20: Abrir Versões
A21: Abrir Motores
A22: Abrir Requisitos
A23: Abrir ADRs
A24: Abrir Gates
A25: Abrir Riscos
A26: Abrir Dependências

Sheet Tarefas
A1: Ordem | B1: ID | C1: Versão | D1: Sprint | E1: Componente | F1: Forma de integração | G1: Tipo | H1: Tarefa | I1: Passo de execução | J1: Artefato a produzir | K1: Critério de aceite | L1: Dependências | M1: Requisitos | N1: Status | O1: Prioridade na versão | P1: Risco | Q1: Aplicabilidade | R1: Responsável | S1: Revisor humano | T1: Data de aceite | U1: Evidência exigida | V1: Evidência obtida | W1: ADR / justificativa | X1: Fechamento | Y1: Observações
A2: 1 | B2: SL-S01-01 | C2: v0.0.1 | D2: S01 | E2: Arquitetura / produto | F2: Próprio | G2: Decisão | H2: Congelar documentos de entrada | I2: Copiar RFC e plano de integração para referências; registrar hashes e divergências. | J2: docs/baseline/manifest.json | K2: Os dois documentos permanecem íntegros e cada divergência aponta à seção de origem. | M2: R01; R03; R07; R08; R33; R34 | N2: Não iniciado | O2: P0 | P2: Crítico | Q2: Obrigatória no escopo da versão | R2: Autor | U2: reports/S01/SL-S01-01.md | X2: =IF(N2="Concluído",IF(AND(S2<>"",ISNUMBER(T2),T2>0,V2<>"",TRUE),"OK","REVISAR"),IF(N2="Dispensado (ADR)",IF(AND(LEFT(Q2,11)="Condicional",W2<>"",S2<>"",ISNUMBER(T2),T2>0,V2<>""),"DISPENSADO","REVISAR"),"PENDENTE"))
A3: 2 | B3: SL-S01-02 | C3: v0.0.1 | D3: S01 | E3: Arquitetura / produto | F3: Próprio | G3: Decisão | H3: Delimitar v1.0 | I3: Enumerar jornadas Captura→Mesa→Peça e separar requisitos de propostas pós-v1.0. | J3: docs/product/scope-v1.md | K3: Nenhuma funcionalidade original é silenciosamente adiada para v2; exclusões estão explícitas. | L3: SL-S01-01 | M3: R01; R03; R07; R08; R33; R34 | N3: Não iniciado | O3: P0 | P3: Crítico | Q3: Obrigatória no escopo da versão | R3: Autor | U3: reports/S01/SL-S01-02.md | X3: =IF(N3="Concluído",IF(AND(S3<>"",ISNUMBER(T3),T3>0,V3<>"",AND(OR(X2="OK",X2="DISPENSADO"))),"OK","REVISAR"),IF(N3="Dispensado (ADR)",IF(AND(LEFT(Q3,11)="Condicional",W3<>"",S3<>"",ISNUMBER(T3),T3>0,V3<>""),"DISPENSADO","REVISAR"),"PENDENTE"))
A4: 3 | B4: SL-S01-03 | C4: v0.0.1 | D4: S01 | E4: Arquitetura / produto | F4: Próprio | G4: Decisão | H4: Ratificar núcleo e workers | I4: Resolver ADR-001; distinguir linguagem do Core, runtime e modelo de distribuição. | J4: docs/adr/001-composicao.md | K4: Decisão aprovada pelo autor; rejeição de workers bloqueia o restante e exige novo plano. | L4: SL-S01-02 | M4: R01; R03; R07; R08; R33; R34 | N4: Não iniciado | O4: P0 | P4: Crítico | Q4: Obrigatória no escopo da versão | R4: Autor | U4: reports/S01/SL-S01-03.md | X4: =IF(N4="Concluído",IF(AND(S4<>"",ISNUMBER(T4),T4>0,V4<>"",AND(OR(X3="OK",X3="DISPENSADO"))),"OK","REVISAR"),IF(N4="Dispensado (ADR)",IF(AND(LEFT(Q4,11)="Condicional",W4<>"",S4<>"",ISNUMBER(T4),T4>0,V4<>""),"DISPENSADO","REVISAR"),"PENDENTE"))
A5: 4 | B5: SL-S01-04 | C5: v0.0.1 | D5: S01 | E5: Arquitetura / produto | F5: Próprio | G5: Decisão | H5: Ratificar Jev/offline | I5: Escolher fallback local ou pendência; definir quando a API pode receber conteúdo. | J5: docs/adr/004-egress-offline.md | K5: Falta de chave/rede não bloqueia captura, leitura ou autoria; nenhuma chamada implícita permitida. | L5: SL-S01-03 | M5: R01; R03; R07; R08; R33; R34 | N5: Não iniciado | O5: P0 | P5: Crítico | Q5: Obrigatória no escopo da versão | R5: Autor | U5: reports/S01/SL-S01-04.md | X5: =IF(N5="Concluído",IF(AND(S5<>"",ISNUMBER(T5),T5>0,V5<>"",AND(OR(X4="OK",X4="DISPENSADO"))),"OK","REVISAR"),IF(N5="Dispensado (ADR)",IF(AND(LEFT(Q5,11)="Condicional",W5<>"",S5<>"",ISNUMBER(T5),T5>0,V5<>""),"DISPENSADO","REVISAR"),"PENDENTE"))
A6: 5 | B6: SL-S01-05 | C6: v0.0.1 | D6: S01 | E6: Arquitetura / produto | F6: Próprio | G6: Decisão | H6: Escolher host de referência | I6: Registrar máquina principal e acesso de teste aos cinco alvos previstos. | J6: docs/adr/006-targets.md | K6: Plataforma de desenvolvimento escolhida e lacunas de hardware identificadas, sem alegar homologação. | L6: SL-S01-04 | M6: R01; R03; R07; R08; R33; R34 | N6: Não iniciado | O6: P0 | P6: Crítico | Q6: Obrigatória no escopo da versão | R6: Autor | U6: reports/S01/SL-S01-05.md | X6: =IF(N6="Concluído",IF(AND(S6<>"",ISNUMBER(T6),T6>0,V6<>"",AND(OR(X5="OK",X5="DISPENSADO"))),"OK","REVISAR"),IF(N6="Dispensado (ADR)",IF(AND(LEFT(Q6,11)="Condicional",W6<>"",S6<>"",ISNUMBER(T6),T6>0,V6<>""),"DISPENSADO","REVISAR"),"PENDENTE"))
A7: 6 | B7: SL-S01-06 | C7: v0.0.1 | D7: S01 | E7: Arquitetura / produto | F7: Próprio | G7: Decisão | H7: Fixar semântica de versões | I7: Separar versão do app, formato do Vault, contratos de workers e modelos. | J7: docs/product/version-policy.md | K7: Atualizar o app não implica migrar o Vault; regras pre-1.0 e compatibilidade estão claras. | L7: SL-S01-05 | M7: R01; R03; R07; R08; R33; R34 | N7: Não iniciado | O7: P0 | P7: Crítico | Q7: Obrigatória no escopo da versão | R7: Autor | U7: reports/S01/SL-S01-06.md | X7: =IF(N7="Concluído",IF(AND(S7<>"",ISNUMBER(T7),T7>0,V7<>"",AND(OR(X6="OK",X6="DISPENSADO"))),"OK","REVISAR"),IF(N7="Dispensado (ADR)",IF(AND(LEFT(Q7,11)="Condicional",W7<>"",S7<>"",ISNUMBER(T7),T7>0,V7<>""),"DISPENSADO","REVISAR"),"PENDENTE"))
A8: 7 | B8: SL-S01-07 | C8: v0.0.1 | D8: S01 | E8: Arquitetura / produto | F8: Próprio | G8: Decisão | H8: Definir dados sensíveis | I8: Classificar conteúdo, consultas, metadados, chaves e logs; negar envio por padrão. | J8: docs/security/data-classification.md | K8: Casos de resumo e título sensível também exigem política de saída, não apenas documentos completos. | L8: SL-S01-06 | M8: R01; R03; R07; R08; R33; R34 | N8: Não iniciado | O8: P0 | P8: Crítico | Q8: Obrigatória no escopo da versão | R8: Autor | U8: reports/S01/SL-S01-07.md | X8: =IF(N8="Concluído",IF(AND(S8<>"",ISNUMBER(T8),T8>0,V8<>"",AND(OR(X7="OK",X7="DISPENSADO"))),"OK","REVISAR"),IF(N8="Dispensado (ADR)",IF(AND(LEFT(Q8,11)="Condicional",W8<>"",S8<>"",ISNUMBER(T8),T8>0,V8<>""),"DISPENSADO","REVISAR"),"PENDENTE"))
A9: 8 | B9: SL-S01-08 | C9: v0.0.1 | D9: S01 | E9: Arquitetura / produto | F9: Próprio | G9: Decisão | H9: Mapear atores e ameaças | I9: Incluir arquivo malformado, página hostil, extensão, modelo e processo local malicioso. | J9: docs/security/threat-model.md | K9: Cada ator tem ativos, fronteiras e ataques de teste; modelo não aparece como autoridade confiável. | L9: SL-S01-07 | M9: R01; R03; R07; R08; R33; R34 | N9: Não iniciado | O9: P0 | P9: Crítico | Q9: Obrigatória no escopo da versão | R9: Autor | U9: reports/S01/SL-S01-08.md | X9: =IF(N9="Concluído",IF(AND(S9<>"",ISNUMBER(T9),T9>0,V9<>"",AND(OR(X8="OK",X8="DISPENSADO"))),"OK","REVISAR"),IF(N9="Dispensado (ADR)",IF(AND(LEFT(Q9,11)="Condicional",W9<>"",S9<>"",ISNUMBER(T9),T9>0,V9<>""),"DISPENSADO","REVISAR"),"PENDENTE"))
A10: 9 | B10: SL-S01-09 | C10: v0.0.1 | D10: S01 | E10: Arquitetura / produto | F10: Próprio | G10: Decisão | H10: Registrar não escopo | I10: Excluir SaaS obrigatório, colaboração em tempo real e marketplace irrestrito deste horizonte. | J10: docs/product/non-goals.md | K10: Funcionalidades não aprovadas não entram por implicação da presença de Yjs, LocalAI ou MCP. | L10: SL-S01-08 | M10: R01; R03; R07; R08; R33; R34 | N10: Não iniciado | O10: P0 | P10: Crítico | Q10: Obrigatória no escopo da versão | R10: Autor | U10: reports/S01/SL-S01-09.md | X10: =IF(N10="Concluído",IF(AND(S10<>"",ISNUMBER(T10),T10>0,V10<>"",AND(OR(X9="OK",X9="DISPENSADO"))),"OK","REVISAR"),IF(N10="Dispensado (ADR)",IF(AND(LEFT(Q10,11)="Condicional",W10<>"",S10<>"",ISNUMBER(T10),T10>0,V10<>""),"DISPENSADO","REVISAR"),"PENDENTE"))
A11: 10 | B11: SL-S01-10 | C11: v0.0.1 | D11: S01 | E11: Arquitetura / produto | F11: Próprio | G11: Decisão | H11: Aprovar inventário de requisitos | I11: Numerar invariantes, métricas e critérios; designar o autor como aprovador dos gates. | J11: docs/product/requirements.yaml | K11: Cada requisito tem origem, critério e responsável; ambiguidades não são tratadas como concluídas. | L11: SL-S01-09 | M11: R01; R03; R07; R08; R33; R34 | N11: Não iniciado | O11: P0 | P11: Crítico | Q11: Obrigatória no escopo da versão | R11: Autor | U11: reports/S01/SL-S01-10.md | X11: =IF(N11="Concluído",IF(AND(S11<>"",ISNUMBER(T11),T11>0,V11<>"",AND(OR(X10="OK",X10="DISPENSADO"))),"OK","REVISAR"),IF(N11="Dispensado (ADR)",IF(AND(LEFT(Q11,11)="Condicional",W11<>"",S11<>"",ISNUMBER(T11),T11>0,V11<>""),"DISPENSADO","REVISAR"),"PENDENTE"))
A12: 11 | B12: SL-S01-GATE | C12: v0.0.1 | D12: S01 | E12: Arquitetura / produto | F12: Aceite humano | G12: Gate | H12: Aceitar S01 — Ratificar escopo, soberania e composição | I12: Revisar as dez tarefas, executar a demonstração do sprint, confrontar critérios e registrar decisão go/no-go. | J12: reports/S01/acceptance.md | K12: Autor consegue explicar offline, Jev, workers e cinco alvos sem contradições. Todas as dependências aceitas; evidências vinculadas a revisão/ambiente; nenhum blocker de integridade/segurança. | L12: SL-S01-01; SL-S01-02; SL-S01-03; SL-S01-04; SL-S01-05; SL-S01-06; SL-S01-07; SL-S01-08; SL-S01-09; SL-S01-10 | M12: R01; R03; R07; R08; R33; R34 | N12: Não iniciado | O12: P0 | P12: Crítico | Q12: Obrigatória para fechar a versão aprovada | R12: Autor | U12: reports/S01/acceptance.md | X12: =IF(N12="Concluído",IF(AND(S12<>"",ISNUMBER(T12),T12>0,V12<>"",AND(OR(X2="OK",X2="DISPENSADO"),OR(X3="OK",X3="DISPENSADO"),OR(X4="OK",X4="DISPENSADO"),OR(X5="OK",X5="DISPENSADO"),OR(X6="OK",X6="DISPENSADO"),OR(X7="OK",X7="DISPENSADO"),OR(X8="OK",X8="DISPENSADO"),OR(X9="OK",X9="DISPENSADO"),OR(X10="OK",X10="DISPENSADO"),OR(X11="OK",X11="DISPENSADO"))),"OK","REVISAR"),IF(N12="Dispensado (ADR)",IF(AND(LEFT(Q12,11)="Condicional",W12<>"",S12<>"",ISNUMBER(T12),T12>0,V12<>""),"DISPENSADO","REVISAR"),"PENDENTE"))
A13: 12 | B13: SL-S02-01 | C13: v0.0.1 | D13: S02 | E13: Vault / contratos | F13: Próprio | G13: Contrato | H13: Definir entidade e ocorrência | I13: Separar fonte, conteúdo da célula/nota, ocorrência visual, grupo, aresta, Peça e bloco. | J13: schemas/domain-v0.json | K13: A mesma nota em dois boards tem conteúdo único e duas geometrias independentes. | L13: SL-S01-GATE | M13: R02; R04; R05; R11; R13; R32; R37 | N13: Não iniciado | O13: P0 | P13: Crítico | Q13: Obrigatória no escopo da versão | R13: Autor + agente de IA | U13: reports/S02/SL-S02-01.md | X13: =IF(N13="Concluído",IF(AND(S13<>"",ISNUMBER(T13),T13>0,V13<>"",AND(OR(X12="OK",X12="DISPENSADO"))),"OK","REVISAR"),IF(N13="Dispensado (ADR)",IF(AND(LEFT(Q13,11)="Condicional",W13<>"",S13<>"",ISNUMBER(T13),T13>0,V13<>""),"DISPENSADO","REVISAR"),"PENDENTE"))
A14: 13 | B14: SL-S02-02 | C14: v0.0.1 | D14: S02 | E14: Vault / contratos | F14: Próprio | G14: Contrato | H14: Definir IDs estáveis | I14: Fixar geração, namespace e regras de colisão sem depender do nome do arquivo. | J14: schemas/identity-v0.json | K14: Renomear/mover não altera identidade; duplicar como nova autoria recebe novo ID. | L14: SL-S02-01 | M14: R02; R04; R05; R11; R13; R32; R37 | N14: Não iniciado | O14: P0 | P14: Crítico | Q14: Obrigatória no escopo da versão | R14: Autor + agente de IA | U14: reports/S02/SL-S02-02.md | X14: =IF(N14="Concluído",IF(AND(S14<>"",ISNUMBER(T14),T14>0,V14<>"",AND(OR(X13="OK",X13="DISPENSADO"))),"OK","REVISAR"),IF(N14="Dispensado (ADR)",IF(AND(LEFT(Q14,11)="Condicional",W14<>"",S14<>"",ISNUMBER(T14),T14>0,V14<>""),"DISPENSADO","REVISAR"),"PENDENTE"))
A15: 14 | B15: SL-S02-03 | C15: v0.0.1 | D15: S02 | E15: Vault / contratos | F15: Próprio | G15: Decisão | H15: Definir autoridade de arquivos | I15: Formalizar JSON+histórico e MPK derivado; resolver ADR-002. | J15: docs/adr/002-file-truth.md | K15: Recuperação tem precedência determinística e não escolhe fonte por timestamp arbitrário. | L15: SL-S02-02 | M15: R02; R04; R05; R11; R13; R32; R37 | N15: Não iniciado | O15: P0 | P15: Crítico | Q15: Obrigatória no escopo da versão | R15: Autor | U15: reports/S02/SL-S02-03.md | X15: =IF(N15="Concluído",IF(AND(S15<>"",ISNUMBER(T15),T15>0,V15<>"",AND(OR(X14="OK",X14="DISPENSADO"))),"OK","REVISAR"),IF(N15="Dispensado (ADR)",IF(AND(LEFT(Q15,11)="Condicional",W15<>"",S15<>"",ISNUMBER(T15),T15>0,V15<>""),"DISPENSADO","REVISAR"),"PENDENTE"))
A16: 15 | B16: SL-S02-04 | C16: v0.0.1 | D16: S02 | E16: Vault / contratos | F16: Próprio | G16: Contrato | H16: Especificar perfil Markdown | I16: Listar blocos suportados e representação de frontmatter, IDs, tabelas e citações. | J16: docs/adr/005-markdown-profile.md | K16: Cada bloco possui round-trip previsto; recurso não representável é preservado ou recusado, não achatado. | L16: SL-S02-03 | M16: R02; R04; R05; R11; R13; R32; R37 | N16: Não iniciado | O16: P0 | P16: Crítico | Q16: Obrigatória no escopo da versão | R16: Autor + agente de IA | U16: reports/S02/SL-S02-04.md | X16: =IF(N16="Concluído",IF(AND(S16<>"",ISNUMBER(T16),T16>0,V16<>"",AND(OR(X15="OK",X15="DISPENSADO"))),"OK","REVISAR"),IF(N16="Dispensado (ADR)",IF(AND(LEFT(Q16,11)="Condicional",W16<>"",S16<>"",ISNUMBER(T16),T16>0,V16<>""),"DISPENSADO","REVISAR"),"PENDENTE"))
A17: 16 | B17: SL-S02-05 | C17: v0.0.1 | D17: S02 | E17: Vault / contratos | F17: Próprio | G17: Contrato | H17: Especificar topologia | I17: Registrar posições, dimensões, grupos, conexões, rótulos e referências de conteúdo. | J17: schemas/board-v0.json | K17: Ciclos e arestas entre grupos são representáveis sem duplicar conteúdo. | L17: SL-S02-04 | M17: R02; R04; R05; R11; R13; R32; R37 | N17: Não iniciado | O17: P0 | P17: Crítico | Q17: Obrigatória no escopo da versão | R17: Autor + agente de IA | U17: reports/S02/SL-S02-05.md | X17: =IF(N17="Concluído",IF(AND(S17<>"",ISNUMBER(T17),T17>0,V17<>"",AND(OR(X16="OK",X16="DISPENSADO"))),"OK","REVISAR"),IF(N17="Dispensado (ADR)",IF(AND(LEFT(Q17,11)="Condicional",W17<>"",S17<>"",ISNUMBER(T17),T17>0,V17<>""),"DISPENSADO","REVISAR"),"PENDENTE"))
A18: 17 | B18: SL-S02-06 | C18: v0.0.1 | D18: S02 | E18: Vault / contratos | F18: Próprio | G18: Contrato | H18: Especificar revisões e eventos | I18: Definir base_revision, operação, autor, origem IA e marcador de confirmação. | J18: schemas/event-v0.json | K18: Evento não confirmado é distinguível de estado salvo; replay e conflitos têm regras explícitas. | L18: SL-S02-05 | M18: R02; R04; R05; R11; R13; R32; R37 | N18: Não iniciado | O18: P0 | P18: Crítico | Q18: Obrigatória no escopo da versão | R18: Autor + agente de IA | U18: reports/S02/SL-S02-06.md | X18: =IF(N18="Concluído",IF(AND(S18<>"",ISNUMBER(T18),T18>0,V18<>"",AND(OR(X17="OK",X17="DISPENSADO"))),"OK","REVISAR"),IF(N18="Dispensado (ADR)",IF(AND(LEFT(Q18,11)="Condicional",W18<>"",S18<>"",ISNUMBER(T18),T18>0,V18<>""),"DISPENSADO","REVISAR"),"PENDENTE"))
A19: 18 | B19: SL-S02-07 | C19: v0.0.1 | D19: S02 | E19: Vault / contratos | F19: Próprio | G19: Contrato | H19: Especificar evidência | I19: Combinar source_id, revisão, trecho, localizador, hash e bloco de destino. | J19: schemas/evidence-v0.json | K19: Referência distingue texto citado de comentário e não se torna inválida por renomeação. | L19: SL-S02-06 | M19: R02; R04; R05; R11; R13; R32; R37 | N19: Não iniciado | O19: P0 | P19: Crítico | Q19: Obrigatória no escopo da versão | R19: Autor + agente de IA | U19: reports/S02/SL-S02-07.md | X19: =IF(N19="Concluído",IF(AND(S19<>"",ISNUMBER(T19),T19>0,V19<>"",AND(OR(X18="OK",X18="DISPENSADO"))),"OK","REVISAR"),IF(N19="Dispensado (ADR)",IF(AND(LEFT(Q19,11)="Condicional",W19<>"",S19<>"",ISNUMBER(T19),T19>0,V19<>""),"DISPENSADO","REVISAR"),"PENDENTE"))
A20: 19 | B20: SL-S02-08 | C20: v0.0.1 | D20: S02 | E20: Vault / contratos | F20: Próprio | G20: Contrato | H20: Especificar metadados de IA | I20: Separar resumo gerado/editado, tags sugeridas/aceitas e identificação do pipeline. | J20: schemas/enrichment-v0.json | K20: Reprocessamento não sobrescreve correção humana; cobertura parcial pode ser declarada. | L20: SL-S02-07 | M20: R02; R04; R05; R11; R13; R32; R37 | N20: Não iniciado | O20: P0 | P20: Crítico | Q20: Obrigatória no escopo da versão | R20: Autor + agente de IA | U20: reports/S02/SL-S02-08.md | X20: =IF(N20="Concluído",IF(AND(S20<>"",ISNUMBER(T20),T20>0,V20<>"",AND(OR(X19="OK",X19="DISPENSADO"))),"OK","REVISAR"),IF(N20="Dispensado (ADR)",IF(AND(LEFT(Q20,11)="Condicional",W20<>"",S20<>"",ISNUMBER(T20),T20>0,V20<>""),"DISPENSADO","REVISAR"),"PENDENTE"))
A21: 20 | B21: SL-S02-09 | C21: v0.0.1 | D21: S02 | E21: Vault / contratos | F21: Próprio | G21: Teste | H21: Construir fixtures válidas e inválidas | I21: Criar um Vault mínimo, um completo e casos com campos desconhecidos. | J21: tests/fixtures/schema/ | K21: Validadores aceitam extensões permitidas e rejeitam IDs duplicados, tipos errados e referências impossíveis. | L21: SL-S02-08 | M21: R02; R04; R05; R11; R13; R32; R37 | N21: Não iniciado | O21: P0 | P21: Crítico | Q21: Obrigatória no escopo da versão | R21: Autor + agente de IA | U21: reports/S02/SL-S02-09.md | X21: =IF(N21="Concluído",IF(AND(S21<>"",ISNUMBER(T21),T21>0,V21<>"",AND(OR(X20="OK",X20="DISPENSADO"))),"OK","REVISAR"),IF(N21="Dispensado (ADR)",IF(AND(LEFT(Q21,11)="Condicional",W21<>"",S21<>"",ISNUMBER(T21),T21>0,V21<>""),"DISPENSADO","REVISAR"),"PENDENTE"))
A22: 21 | B22: SL-S02-10 | C22: v0.0.1 | D22: S02 | E22: Vault / contratos | F22: Próprio | G22: Decisão | H22: Definir evolução de schema | I22: Documentar migração, versão desconhecida, abertura somente leitura e exportação. | J22: docs/contracts/schema-evolution.md | K22: Um app antigo nunca regrava silenciosamente um formato novo que não compreende. | L22: SL-S02-09 | M22: R02; R04; R05; R11; R13; R32; R37 | N22: Não iniciado | O22: P0 | P22: Crítico | Q22: Obrigatória no escopo da versão | R22: Autor | U22: reports/S02/SL-S02-10.md | X22: =IF(N22="Concluído",IF(AND(S22<>"",ISNUMBER(T22),T22>0,V22<>"",AND(OR(X21="OK",X21="DISPENSADO"))),"OK","REVISAR"),IF(N22="Dispensado (ADR)",IF(AND(LEFT(Q22,11)="Condicional",W22<>"",S22<>"",ISNUMBER(T22),T22>0,V22<>""),"DISPENSADO","REVISAR"),"PENDENTE"))
A23: 22 | B23: SL-S02-GATE | C23: v0.0.1 | D23: S02 | E23: Vault / contratos | F23: Aceite humano | G23: Gate | H23: Aceitar S02 — Definir formatos, identidade e autoridade | I23: Revisar as dez tarefas, executar a demonstração do sprint, confrontar critérios e registrar decisão go/no-go. | J23: reports/S02/acceptance.md | K23: Fixtures independentes dos motores representam uma mesa e uma Peça completas. Todas as dependências aceitas; evidências vinculadas a revisão/ambiente; nenhum blocker de integridade/segurança. | L23: SL-S02-01; SL-S02-02; SL-S02-03; SL-S02-04; SL-S02-05; SL-S02-06; SL-S02-07; SL-S02-08; SL-S02-09; SL-S02-10 | M23: R02; R04; R05; R11; R13; R32; R37 | N23: Não iniciado | O23: P0 | P23: Crítico | Q23: Obrigatória para fechar a versão aprovada | R23: Autor | U23: reports/S02/acceptance.md | X23: =IF(N23="Concluído",IF(AND(S23<>"",ISNUMBER(T23),T23>0,V23<>"",AND(OR(X13="OK",X13="DISPENSADO"),OR(X14="OK",X14="DISPENSADO"),OR(X15="OK",X15="DISPENSADO"),OR(X16="OK",X16="DISPENSADO"),OR(X17="OK",X17="DISPENSADO"),OR(X18="OK",X18="DISPENSADO"),OR(X19="OK",X19="DISPENSADO"),OR(X20="OK",X20="DISPENSADO"),OR(X21="OK",X21="DISPENSADO"),OR(X22="OK",X22="DISPENSADO"))),"OK","REVISAR"),IF(N23="Dispensado (ADR)",IF(AND(LEFT(Q23,11)="Condicional",W23<>"",S23<>"",ISNUMBER(T23),T23>0,V23<>""),"DISPENSADO","REVISAR"),"PENDENTE"))
A24: 23 | B24: SL-S03-01 | C24: v0.0.1 | D24: S03 | E24: Todos os motores / licenças | F24: Desconstrução | G24: Upstream | H24: Inventariar repositórios | I24: Registrar URL, licença observada, linguagens, releases e componentes transitivos críticos. | J24: upstream/catalog.yaml | K24: BlockSuite, PageIndex, Docling, Jev, Qdrant, HelixDB, Scrapling, SearxNG e LocalAI estão cobertos. | L24: SL-S01-GATE; SL-S02-GATE | M24: R03; R30; R33; R34 | N24: Não iniciado | O24: P0 | P24: Crítico | Q24: Obrigatória no escopo da versão | R24: Autor + agente de IA | U24: reports/S03/SL-S03-01.md | X24: =IF(N24="Concluído",IF(AND(S24<>"",ISNUMBER(T24),T24>0,V24<>"",AND(OR(X12="OK",X12="DISPENSADO"),OR(X23="OK",X23="DISPENSADO"))),"OK","REVISAR"),IF(N24="Dispensado (ADR)",IF(AND(LEFT(Q24,11)="Condicional",W24<>"",S24<>"",ISNUMBER(T24),T24>0,V24<>""),"DISPENSADO","REVISAR"),"PENDENTE"))
A25: 24 | B25: SL-S03-02 | C25: v0.0.1 | D25: S03 | E25: Todos os motores / licenças | F25: Desconstrução | G25: Upstream | H25: Criar manifesto de origem | I25: Definir campos commit/tag, hashes, patches, avisos e comando de build. | J25: upstream/manifest.schema.json | K25: Nenhum componente empacotado pode usar latest ou branch móvel sem resolução para uma revisão. | L25: SL-S03-01 | M25: R03; R30; R33; R34 | N25: Não iniciado | O25: P0 | P25: Crítico | Q25: Obrigatória no escopo da versão | R25: Autor + agente de IA | U25: reports/S03/SL-S03-02.md | X25: =IF(N25="Concluído",IF(AND(S25<>"",ISNUMBER(T25),T25>0,V25<>"",AND(OR(X24="OK",X24="DISPENSADO"))),"OK","REVISAR"),IF(N25="Dispensado (ADR)",IF(AND(LEFT(Q25,11)="Condicional",W25<>"",S25<>"",ISNUMBER(T25),T25>0,V25<>""),"DISPENSADO","REVISAR"),"PENDENTE"))
A26: 25 | B26: SL-S03-03 | C26: v0.0.1 | D26: S03 | E26: Todos os motores / licenças | F26: Desconstrução | G26: Licença | H26: Examinar BlockSuite por árvore | I26: Distinguir standalone de AFFiNE e fechar o inventário dos arquivos candidatos. | J26: docs/legal/blocksuite-scope.md | K26: Licença não é inferida apenas pelo nome do projeto ou por um único package.json. | L26: SL-S03-02 | M26: R03; R30; R33; R34 | N26: Não iniciado | O26: P0 | P26: Crítico | Q26: Obrigatória no escopo da versão | R26: Autor | U26: reports/S03/SL-S03-03.md | X26: =IF(N26="Concluído",IF(AND(S26<>"",ISNUMBER(T26),T26>0,V26<>"",AND(OR(X25="OK",X25="DISPENSADO"))),"OK","REVISAR"),IF(N26="Dispensado (ADR)",IF(AND(LEFT(Q26,11)="Condicional",W26<>"",S26<>"",ISNUMBER(T26),T26>0,V26<>""),"DISPENSADO","REVISAR"),"PENDENTE"))
A27: 26 | B27: SL-S03-04 | C27: v0.0.1 | D27: S03 | E27: Todos os motores / licenças | F27: Desconstrução | G27: Licença | H27: Examinar SearxNG e modelos | I27: Separar código AGPL, integração por API e termos dos pesos/backends. | J27: docs/legal/component-obligations.md | K27: Fonte correspondente, avisos e redistribuição estão mapeados por artefato. | L27: SL-S03-03 | M27: R03; R30; R33; R34 | N27: Não iniciado | O27: P0 | P27: Crítico | Q27: Obrigatória no escopo da versão | R27: Autor | U27: reports/S03/SL-S03-04.md | X27: =IF(N27="Concluído",IF(AND(S27<>"",ISNUMBER(T27),T27>0,V27<>"",AND(OR(X26="OK",X26="DISPENSADO"))),"OK","REVISAR"),IF(N27="Dispensado (ADR)",IF(AND(LEFT(Q27,11)="Condicional",W27<>"",S27<>"",ISNUMBER(T27),T27>0,V27<>""),"DISPENSADO","REVISAR"),"PENDENTE"))
A28: 27 | B28: SL-S03-05 | C28: v0.0.1 | D28: S03 | E28: Todos os motores / licenças | F28: Desconstrução | G28: Decisão | H28: Ratificar licença própria | I28: Resolver ADR-003; explicar operação não comercial versus direitos open source de terceiros. | J28: docs/adr/003-license.md | K28: Licença aprovada sem cláusula non-commercial incompatível disfarçada de open source. | L28: SL-S03-04 | M28: R03; R30; R33; R34 | N28: Não iniciado | O28: P0 | P28: Crítico | Q28: Obrigatória no escopo da versão | R28: Autor | U28: reports/S03/SL-S03-05.md | X28: =IF(N28="Concluído",IF(AND(S28<>"",ISNUMBER(T28),T28>0,V28<>"",AND(OR(X27="OK",X27="DISPENSADO"))),"OK","REVISAR"),IF(N28="Dispensado (ADR)",IF(AND(LEFT(Q28,11)="Condicional",W28<>"",S28<>"",ISNUMBER(T28),T28>0,V28<>""),"DISPENSADO","REVISAR"),"PENDENTE"))
A29: 28 | B29: SL-S03-06 | C29: v0.0.1 | D29: S03 | E29: Todos os motores / licenças | F29: Desconstrução | G29: Upstream | H29: Delimitar reutilização | I29: Marcar bibliotecas, adapters, forks mínimos e serviços; excluir UIs completas e stores concorrentes. | J29: docs/architecture/reuse-map.md | K29: Cada motor tem lista de incluir/excluir e interfaces Sandland responsáveis pela autoridade. | L29: SL-S03-05 | M29: R03; R30; R33; R34 | N29: Não iniciado | O29: P0 | P29: Crítico | Q29: Obrigatória no escopo da versão | R29: Autor + agente de IA | U29: reports/S03/SL-S03-06.md | X29: =IF(N29="Concluído",IF(AND(S29<>"",ISNUMBER(T29),T29>0,V29<>"",AND(OR(X28="OK",X28="DISPENSADO"))),"OK","REVISAR"),IF(N29="Dispensado (ADR)",IF(AND(LEFT(Q29,11)="Condicional",W29<>"",S29<>"",ISNUMBER(T29),T29>0,V29<>""),"DISPENSADO","REVISAR"),"PENDENTE"))
A30: 29 | B30: SL-S03-07 | C30: v0.0.1 | D30: S03 | E30: Todos os motores / licenças | F30: Desconstrução | G30: Upstream | H30: Definir política de patches | I30: Criar série pequena e reprodutível; separar correções genéricas de customizações. | J30: upstream/PATCH_POLICY.md | K30: Um fork pode ser rebaseado e sua diferença para upstream pode ser enumerada. | L30: SL-S03-06 | M30: R03; R30; R33; R34 | N30: Não iniciado | O30: P0 | P30: Crítico | Q30: Obrigatória no escopo da versão | R30: Autor + agente de IA | U30: reports/S03/SL-S03-07.md | X30: =IF(N30="Concluído",IF(AND(S30<>"",ISNUMBER(T30),T30>0,V30<>"",AND(OR(X29="OK",X29="DISPENSADO"))),"OK","REVISAR"),IF(N30="Dispensado (ADR)",IF(AND(LEFT(Q30,11)="Condicional",W30<>"",S30<>"",ISNUMBER(T30),T30>0,V30<>""),"DISPENSADO","REVISAR"),"PENDENTE"))
A31: 30 | B31: SL-S03-08 | C31: v0.0.1 | D31: S03 | E31: Todos os motores / licenças | F31: Desconstrução | G31: Governança | H31: Preparar avisos e SBOM | I31: Criar estrutura de LICENSES, NOTICE e inventário de dependências. | J31: compliance/ | K31: Não há licença de terceiros substituída pela licença própria sem base legal. | L31: SL-S03-07 | M31: R03; R30; R33; R34 | N31: Não iniciado | O31: P0 | P31: Crítico | Q31: Obrigatória no escopo da versão | R31: Autor | U31: reports/S03/SL-S03-08.md | X31: =IF(N31="Concluído",IF(AND(S31<>"",ISNUMBER(T31),T31>0,V31<>"",AND(OR(X30="OK",X30="DISPENSADO"))),"OK","REVISAR"),IF(N31="Dispensado (ADR)",IF(AND(LEFT(Q31,11)="Condicional",W31<>"",S31<>"",ISNUMBER(T31),T31>0,V31<>""),"DISPENSADO","REVISAR"),"PENDENTE"))
A32: 31 | B32: SL-S03-09 | C32: v0.0.1 | D32: S03 | E32: Todos os motores / licenças | F32: Desconstrução | G32: Governança | H32: Definir ciclo de atualização | I32: Fixar auditoria, testes diferenciais, rollback e prioridade para vulnerabilidades. | J32: docs/maintenance/upstream.md | K32: Atualização sem evidência não chega automaticamente ao usuário ou altera modelos instalados. | L32: SL-S03-08 | M32: R03; R30; R33; R34 | N32: Não iniciado | O32: P0 | P32: Crítico | Q32: Obrigatória no escopo da versão | R32: Autor | U32: reports/S03/SL-S03-09.md | X32: =IF(N32="Concluído",IF(AND(S32<>"",ISNUMBER(T32),T32>0,V32<>"",AND(OR(X31="OK",X31="DISPENSADO"))),"OK","REVISAR"),IF(N32="Dispensado (ADR)",IF(AND(LEFT(Q32,11)="Condicional",W32<>"",S32<>"",ISNUMBER(T32),T32>0,V32<>""),"DISPENSADO","REVISAR"),"PENDENTE"))
A33: 32 | B33: SL-S03-10 | C33: v0.0.1 | D33: S03 | E33: Todos os motores / licenças | F33: Desconstrução | G33: Decisão | H33: Definir limites de spikes | I33: Para cada prova, listar pergunta, corpus, evidência mínima e decisão de continuar/replanejar. | J33: docs/spikes/register.md | K33: Relatório inconclusivo não vira integração aprovada; Qdrant e Helix têm protocolo comparável. | L33: SL-S03-09 | M33: R03; R30; R33; R34 | N33: Não iniciado | O33: P0 | P33: Crítico | Q33: Obrigatória no escopo da versão | R33: Autor | U33: reports/S03/SL-S03-10.md | X33: =IF(N33="Concluído",IF(AND(S33<>"",ISNUMBER(T33),T33>0,V33<>"",AND(OR(X32="OK",X32="DISPENSADO"))),"OK","REVISAR"),IF(N33="Dispensado (ADR)",IF(AND(LEFT(Q33,11)="Condicional",W33<>"",S33<>"",ISNUMBER(T33),T33>0,V33<>""),"DISPENSADO","REVISAR"),"PENDENTE"))
A34: 33 | B34: SL-S03-GATE | C34: v0.0.1 | D34: S03 | E34: Todos os motores / licenças | F34: Aceite humano | G34: Gate | H34: Aceitar S03 — Inventariar upstreams e definir recortes | I34: Revisar as dez tarefas, executar a demonstração do sprint, confrontar critérios e registrar decisão go/no-go. | J34: reports/S03/acceptance.md | K34: Cada motor tem origem rastreável, fronteira proposta e decisão de manter/extrair/adaptar. Todas as dependências aceitas; evidências vinculadas a revisão/ambiente; nenhum blocker de integridade/segurança. | L34: SL-S03-01; SL-S03-02; SL-S03-03; SL-S03-04; SL-S03-05; SL-S03-06; SL-S03-07; SL-S03-08; SL-S03-09; SL-S03-10 | M34: R03; R30; R33; R34 | N34: Não iniciado | O34: P0 | P34: Crítico | Q34: Obrigatória para fechar a versão aprovada | R34: Autor | U34: reports/S03/acceptance.md | X34: =IF(N34="Concluído",IF(AND(S34<>"",ISNUMBER(T34),T34>0,V34<>"",AND(OR(X24="OK",X24="DISPENSADO"),OR(X25="OK",X25="DISPENSADO"),OR(X26="OK",X26="DISPENSADO"),OR(X27="OK",X27="DISPENSADO"),OR(X28="OK",X28="DISPENSADO"),OR(X29="OK",X29="DISPENSADO"),OR(X30="OK",X30="DISPENSADO"),OR(X31="OK",X31="DISPENSADO"),OR(X32="OK",X32="DISPENSADO"),OR(X33="OK",X33="DISPENSADO"))),"OK","REVISAR"),IF(N34="Dispensado (ADR)",IF(AND(LEFT(Q34,11)="Condicional",W34<>"",S34<>"",ISNUMBER(T34),T34>0,V34<>""),"DISPENSADO","REVISAR"),"PENDENTE"))
A35: 34 | B35: SL-S04-01 | C35: v0.0.2 | D35: S04 | E35: Ferramentas / governança | F35: Próprio | G35: Implementação | H35: Criar estrutura do monorepo | I35: Separar app desktop, crates, adapters, workers, schemas, fixtures e docs. | J35: repository-layout.md | K35: Dependências apontam para contratos e não para UI/estado privado de outro motor. | L35: SL-S03-GATE | M35: R03; R30; R33; R34 | N35: Não iniciado | O35: P0 | P35: Crítico | Q35: Obrigatória no escopo da versão | R35: Autor + agente de IA | U35: reports/S04/SL-S04-01.md | X35: =IF(N35="Concluído",IF(AND(S35<>"",ISNUMBER(T35),T35>0,V35<>"",AND(OR(X34="OK",X34="DISPENSADO"))),"OK","REVISAR"),IF(N35="Dispensado (ADR)",IF(AND(LEFT(Q35,11)="Condicional",W35<>"",S35<>"",ISNUMBER(T35),T35>0,V35<>""),"DISPENSADO","REVISAR"),"PENDENTE"))
A36: 35 | B36: SL-S04-02 | C36: v0.0.2 | D36: S04 | E36: Ferramentas / governança | F36: Próprio | G36: Implementação | H36: Fixar toolchains | I36: Pin Rust, JS e runtimes necessários para desenvolvimento, sem instaladores globais implícitos. | J36: toolchains.lock | K36: Ambiente limpo reproduz versões; mudanças de versão são diff explícito. | L36: SL-S04-01 | M36: R03; R30; R33; R34 | N36: Não iniciado | O36: P0 | P36: Crítico | Q36: Obrigatória no escopo da versão | R36: Autor + agente de IA | U36: reports/S04/SL-S04-02.md | X36: =IF(N36="Concluído",IF(AND(S36<>"",ISNUMBER(T36),T36>0,V36<>"",AND(OR(X35="OK",X35="DISPENSADO"))),"OK","REVISAR"),IF(N36="Dispensado (ADR)",IF(AND(LEFT(Q36,11)="Condicional",W36<>"",S36<>"",ISNUMBER(T36),T36>0,V36<>""),"DISPENSADO","REVISAR"),"PENDENTE"))
A37: 36 | B37: SL-S04-03 | C37: v0.0.2 | D37: S04 | E37: Ferramentas / governança | F37: Próprio | G37: Implementação | H37: Configurar formatadores e lint | I37: Definir regras por linguagem e exclusões de fontes vendorizadas. | J37: tooling/lint/ | K37: Comando único reporta erros sem reformatar ou apagar avisos de arquivos upstream. | L37: SL-S04-02 | M37: R03; R30; R33; R34 | N37: Não iniciado | O37: P0 | P37: Crítico | Q37: Obrigatória no escopo da versão | R37: Autor + agente de IA | U37: reports/S04/SL-S04-03.md | X37: =IF(N37="Concluído",IF(AND(S37<>"",ISNUMBER(T37),T37>0,V37<>"",AND(OR(X36="OK",X36="DISPENSADO"))),"OK","REVISAR"),IF(N37="Dispensado (ADR)",IF(AND(LEFT(Q37,11)="Condicional",W37<>"",S37<>"",ISNUMBER(T37),T37>0,V37<>""),"DISPENSADO","REVISAR"),"PENDENTE"))
A38: 37 | B38: SL-S04-04 | C38: v0.0.2 | D38: S04 | E38: Ferramentas / governança | F38: Próprio | G38: Implementação | H38: Criar comandos de projeto | I38: Padronizar bootstrap, check, test, fixtures e pacote de evidências. | J38: tooling/tasks/ | K38: Comandos têm help, retorno de erro confiável e não dependem do histórico do shell. | L38: SL-S04-03 | M38: R03; R30; R33; R34 | N38: Não iniciado | O38: P0 | P38: Crítico | Q38: Obrigatória no escopo da versão | R38: Autor + agente de IA | U38: reports/S04/SL-S04-04.md | X38: =IF(N38="Concluído",IF(AND(S38<>"",ISNUMBER(T38),T38>0,V38<>"",AND(OR(X37="OK",X37="DISPENSADO"))),"OK","REVISAR"),IF(N38="Dispensado (ADR)",IF(AND(LEFT(Q38,11)="Condicional",W38<>"",S38<>"",ISNUMBER(T38),T38>0,V38<>""),"DISPENSADO","REVISAR"),"PENDENTE"))
A39: 38 | B39: SL-S04-05 | C39: v0.0.2 | D39: S04 | E39: Ferramentas / governança | F39: Próprio | G39: Governança | H39: Criar política de branches | I39: Uma frente mutável principal; PRs pequenos com IDs de tarefa e rollback. | J39: CONTRIBUTING.md | K39: Dois agentes não alteram contratos compartilhados em paralelo sem acordo explícito. | L39: SL-S04-04 | M39: R03; R30; R33; R34 | N39: Não iniciado | O39: P0 | P39: Crítico | Q39: Obrigatória no escopo da versão | R39: Autor | U39: reports/S04/SL-S04-05.md | X39: =IF(N39="Concluído",IF(AND(S39<>"",ISNUMBER(T39),T39>0,V39<>"",AND(OR(X38="OK",X38="DISPENSADO"))),"OK","REVISAR"),IF(N39="Dispensado (ADR)",IF(AND(LEFT(Q39,11)="Condicional",W39<>"",S39<>"",ISNUMBER(T39),T39>0,V39<>""),"DISPENSADO","REVISAR"),"PENDENTE"))
A40: 39 | B40: SL-S04-06 | C40: v0.0.2 | D40: S04 | E40: Ferramentas / governança | F40: Próprio | G40: Governança | H40: Escrever instruções de agentes | I40: Delimitar arquivos, segredos, rede, testes obrigatórios e critérios de parada. | J40: AGENTS.md | K40: Agente não pode declarar testes executados sem logs nem aprovar a própria entrega. | L40: SL-S04-05 | M40: R03; R30; R33; R34 | N40: Não iniciado | O40: P0 | P40: Crítico | Q40: Obrigatória no escopo da versão | R40: Autor | U40: reports/S04/SL-S04-06.md | X40: =IF(N40="Concluído",IF(AND(S40<>"",ISNUMBER(T40),T40>0,V40<>"",AND(OR(X39="OK",X39="DISPENSADO"))),"OK","REVISAR"),IF(N40="Dispensado (ADR)",IF(AND(LEFT(Q40,11)="Condicional",W40<>"",S40<>"",ISNUMBER(T40),T40>0,V40<>""),"DISPENSADO","REVISAR"),"PENDENTE"))
A41: 40 | B41: SL-S04-07 | C41: v0.0.2 | D41: S04 | E41: Ferramentas / governança | F41: Próprio | G41: Governança | H41: Criar template de tarefa | I41: Incluir contrato, fixture, não escopo, aceite e evidências. | J41: .github/ISSUE_TEMPLATE/task.yml | K41: Tarefa pode ser entregue a novo agente sem depender de memória informal da conversa. | L41: SL-S04-06 | M41: R03; R30; R33; R34 | N41: Não iniciado | O41: P0 | P41: Crítico | Q41: Obrigatória no escopo da versão | R41: Autor | U41: reports/S04/SL-S04-07.md | X41: =IF(N41="Concluído",IF(AND(S41<>"",ISNUMBER(T41),T41>0,V41<>"",AND(OR(X40="OK",X40="DISPENSADO"))),"OK","REVISAR"),IF(N41="Dispensado (ADR)",IF(AND(LEFT(Q41,11)="Condicional",W41<>"",S41<>"",ISNUMBER(T41),T41>0,V41<>""),"DISPENSADO","REVISAR"),"PENDENTE"))
A42: 41 | B42: SL-S04-08 | C42: v0.0.2 | D42: S04 | E42: Ferramentas / governança | F42: Próprio | G42: Governança | H42: Criar template de PR | I42: Exigir origem de código, mudanças de schema, segurança, testes e artefatos. | J42: .github/pull_request_template.md | K42: PR sem evidências ou com teste pulado tem bloqueio explícito. | L42: SL-S04-07 | M42: R03; R30; R33; R34 | N42: Não iniciado | O42: P0 | P42: Crítico | Q42: Obrigatória no escopo da versão | R42: Autor | U42: reports/S04/SL-S04-08.md | X42: =IF(N42="Concluído",IF(AND(S42<>"",ISNUMBER(T42),T42>0,V42<>"",AND(OR(X41="OK",X41="DISPENSADO"))),"OK","REVISAR"),IF(N42="Dispensado (ADR)",IF(AND(LEFT(Q42,11)="Condicional",W42<>"",S42<>"",ISNUMBER(T42),T42>0,V42<>""),"DISPENSADO","REVISAR"),"PENDENTE"))
A43: 42 | B43: SL-S04-09 | C43: v0.0.2 | D43: S04 | E43: Ferramentas / governança | F43: Próprio | G43: Implementação | H43: Separar configuração e segredos | I43: Fornecer arquivos de exemplo sem credenciais e política de logs. | J43: config/examples/ | K43: Scanner detecta segredos plantados em fixture e não coleta dados reais do desenvolvedor. | L43: SL-S04-08 | M43: R03; R30; R33; R34 | N43: Não iniciado | O43: P0 | P43: Crítico | Q43: Obrigatória no escopo da versão | R43: Autor + agente de IA | U43: reports/S04/SL-S04-09.md | X43: =IF(N43="Concluído",IF(AND(S43<>"",ISNUMBER(T43),T43>0,V43<>"",AND(OR(X42="OK",X42="DISPENSADO"))),"OK","REVISAR"),IF(N43="Dispensado (ADR)",IF(AND(LEFT(Q43,11)="Condicional",W43<>"",S43<>"",ISNUMBER(T43),T43>0,V43<>""),"DISPENSADO","REVISAR"),"PENDENTE"))
A44: 43 | B44: SL-S04-10 | C44: v0.0.2 | D44: S04 | E44: Ferramentas / governança | F44: Próprio | G44: Teste | H44: Executar ensaio do fluxo | I44: Fazer alteração descartável em fixture, revisão adversarial e reversão. | J44: reports/workflow-dry-run.md | K44: Histórico evidencia proposta, teste, revisão humana e rollback, sem merge automático por agente. | L44: SL-S04-09 | M44: R03; R30; R33; R34 | N44: Não iniciado | O44: P0 | P44: Crítico | Q44: Obrigatória no escopo da versão | R44: Autor + agente de IA | U44: reports/S04/SL-S04-10.md | X44: =IF(N44="Concluído",IF(AND(S44<>"",ISNUMBER(T44),T44>0,V44<>"",AND(OR(X43="OK",X43="DISPENSADO"))),"OK","REVISAR"),IF(N44="Dispensado (ADR)",IF(AND(LEFT(Q44,11)="Condicional",W44<>"",S44<>"",ISNUMBER(T44),T44>0,V44<>""),"DISPENSADO","REVISAR"),"PENDENTE"))
A45: 44 | B45: SL-S04-GATE | C45: v0.0.2 | D45: S04 | E45: Ferramentas / governança | F45: Aceite humano | G45: Gate | H45: Aceitar S04 — Montar repositório e fluxo solo com IA | I45: Revisar as dez tarefas, executar a demonstração do sprint, confrontar critérios e registrar decisão go/no-go. | J45: reports/S04/acceptance.md | K45: Um agente implementa uma tarefa isolada e o autor consegue revisar o patch e seus testes. Todas as dependências aceitas; evidências vinculadas a revisão/ambiente; nenhum blocker de integridade/segurança. | L45: SL-S04-01; SL-S04-02; SL-S04-03; SL-S04-04; SL-S04-05; SL-S04-06; SL-S04-07; SL-S04-08; SL-S04-09; SL-S04-10 | M45: R03; R30; R33; R34 | N45: Não iniciado | O45: P0 | P45: Crítico | Q45: Obrigatória para fechar a versão aprovada | R45: Autor | U45: reports/S04/acceptance.md | X45: =IF(N45="Concluído",IF(AND(S45<>"",ISNUMBER(T45),T45>0,V45<>"",AND(OR(X35="OK",X35="DISPENSADO"),OR(X36="OK",X36="DISPENSADO"),OR(X37="OK",X37="DISPENSADO"),OR(X38="OK",X38="DISPENSADO"),OR(X39="OK",X39="DISPENSADO"),OR(X40="OK",X40="DISPENSADO"),OR(X41="OK",X41="DISPENSADO"),OR(X42="OK",X42="DISPENSADO"),OR(X43="OK",X43="DISPENSADO"),OR(X44="OK",X44="DISPENSADO"))),"OK","REVISAR"),IF(N45="Dispensado (ADR)",IF(AND(LEFT(Q45,11)="Condicional",W45<>"",S45<>"",ISNUMBER(T45),T45>0,V45<>""),"DISPENSADO","REVISAR"),"PENDENTE"))
A46: 45 | B46: SL-S05-01 | C46: v0.0.2 | D46: S05 | E46: Qualidade / desempenho | F46: Próprio | G46: Implementação | H46: Montar CI de contratos | I46: Rodar schemas, lint e testes determinísticos sem chaves de serviços. | J46: .github/workflows/check.yml | K46: PR com schema inválido falha; CI básica passa sem acesso a Jev/BYOK. | L46: SL-S04-GATE | M46: R01; R09; R12; R15; R20; R34 | N46: Não iniciado | O46: P1 | P46: Alto | Q46: Obrigatória no escopo da versão | R46: Autor + agente de IA | U46: reports/S05/SL-S05-01.md | X46: =IF(N46="Concluído",IF(AND(S46<>"",ISNUMBER(T46),T46>0,V46<>"",AND(OR(X45="OK",X45="DISPENSADO"))),"OK","REVISAR"),IF(N46="Dispensado (ADR)",IF(AND(LEFT(Q46,11)="Condicional",W46<>"",S46<>"",ISNUMBER(T46),T46>0,V46<>""),"DISPENSADO","REVISAR"),"PENDENTE"))
A47: 46 | B47: SL-S05-02 | C47: v0.0.2 | D47: S05 | E47: Qualidade / desempenho | F47: Próprio | G47: Implementação | H47: Criar matriz de builds | I47: Incluir os cinco alvos quando suportado pelo ambiente; distinguir build e teste nativo. | J47: ci/target-matrix.yaml | K47: Painel não mostra target compilado como target funcionalmente homologado. | L47: SL-S05-01 | M47: R01; R09; R12; R15; R20; R34 | N47: Não iniciado | O47: P1 | P47: Alto | Q47: Obrigatória no escopo da versão | R47: Autor + agente de IA | U47: reports/S05/SL-S05-02.md | X47: =IF(N47="Concluído",IF(AND(S47<>"",ISNUMBER(T47),T47>0,V47<>"",AND(OR(X46="OK",X46="DISPENSADO"))),"OK","REVISAR"),IF(N47="Dispensado (ADR)",IF(AND(LEFT(Q47,11)="Condicional",W47<>"",S47<>"",ISNUMBER(T47),T47>0,V47<>""),"DISPENSADO","REVISAR"),"PENDENTE"))
A48: 47 | B48: SL-S05-03 | C48: v0.0.2 | D48: S05 | E48: Qualidade / desempenho | F48: Próprio | G48: Teste | H48: Montar corpus documental | I48: Reunir PDFs textuais/escaneados, DOCX, HTML, Markdown e transcrições com direitos de uso. | J48: tests/corpus/manifest.json | K48: Cada item possui hash, idioma, formato e licença/origem; nenhum dado privado entra no repositório. | L48: SL-S05-02 | M48: R01; R09; R12; R15; R20; R34 | N48: Não iniciado | O48: P1 | P48: Alto | Q48: Obrigatória no escopo da versão | R48: Autor + agente de IA | U48: reports/S05/SL-S05-03.md | X48: =IF(N48="Concluído",IF(AND(S48<>"",ISNUMBER(T48),T48>0,V48<>"",AND(OR(X47="OK",X47="DISPENSADO"))),"OK","REVISAR"),IF(N48="Dispensado (ADR)",IF(AND(LEFT(Q48,11)="Condicional",W48<>"",S48<>"",ISNUMBER(T48),T48>0,V48<>""),"DISPENSADO","REVISAR"),"PENDENTE"))
A49: 48 | B49: SL-S05-04 | C49: v0.0.2 | D49: S05 | E49: Qualidade / desempenho | F49: Próprio | G49: Teste | H49: Montar corpus de busca | I49: Rotular perguntas, respostas esperadas, ausência de resposta e fontes em português. | J49: tests/eval/retrieval-v1.jsonl | K49: Conjunto de avaliação é separado dos exemplos usados para ajustar prompts e thresholds. | L49: SL-S05-03 | M49: R01; R09; R12; R15; R20; R34 | N49: Não iniciado | O49: P1 | P49: Alto | Q49: Obrigatória no escopo da versão | R49: Autor + agente de IA | U49: reports/S05/SL-S05-04.md | X49: =IF(N49="Concluído",IF(AND(S49<>"",ISNUMBER(T49),T49>0,V49<>"",AND(OR(X48="OK",X48="DISPENSADO"))),"OK","REVISAR"),IF(N49="Dispensado (ADR)",IF(AND(LEFT(Q49,11)="Condicional",W49<>"",S49<>"",ISNUMBER(T49),T49>0,V49<>""),"DISPENSADO","REVISAR"),"PENDENTE"))
A50: 49 | B50: SL-S05-05 | C50: v0.0.2 | D50: S05 | E50: Qualidade / desempenho | F50: Próprio | G50: Teste | H50: Criar corpus hostil | I50: Incluir traversal, HTML ativo, injeção de prompt, arquivos truncados e URLs internas. | J50: tests/security/fixtures/ | K50: Cada fixture é inerte fora de harness controlado e tem comportamento negado esperado. | L50: SL-S05-04 | M50: R01; R09; R12; R15; R20; R34 | N50: Não iniciado | O50: P1 | P50: Alto | Q50: Obrigatória no escopo da versão | R50: Autor + agente de IA | U50: reports/S05/SL-S05-05.md | X50: =IF(N50="Concluído",IF(AND(S50<>"",ISNUMBER(T50),T50>0,V50<>"",AND(OR(X49="OK",X49="DISPENSADO"))),"OK","REVISAR"),IF(N50="Dispensado (ADR)",IF(AND(LEFT(Q50,11)="Condicional",W50<>"",S50<>"",ISNUMBER(T50),T50>0,V50<>""),"DISPENSADO","REVISAR"),"PENDENTE"))
A51: 50 | B51: SL-S05-06 | C51: v0.0.2 | D51: S05 | E51: Qualidade / desempenho | F51: Próprio | G51: Decisão | H51: Fixar métricas de memória | I51: Definir RAM/RSS/PSS/VRAM, processos incluídos e diferenças por SO. | J51: docs/adr/007-resource-profiles.md | K51: Meta de 350 MB não é validada medindo apenas o processo Rust. | L51: SL-S05-05 | M51: R01; R09; R12; R15; R20; R34 | N51: Não iniciado | O51: P0 | P51: Alto | Q51: Obrigatória no escopo da versão | R51: Autor | U51: reports/S05/SL-S05-06.md | X51: =IF(N51="Concluído",IF(AND(S51<>"",ISNUMBER(T51),T51>0,V51<>"",AND(OR(X50="OK",X50="DISPENSADO"))),"OK","REVISAR"),IF(N51="Dispensado (ADR)",IF(AND(LEFT(Q51,11)="Condicional",W51<>"",S51<>"",ISNUMBER(T51),T51>0,V51<>""),"DISPENSADO","REVISAR"),"PENDENTE"))
A52: 51 | B52: SL-S05-07 | C52: v0.0.2 | D52: S05 | E52: Qualidade / desempenho | F52: Próprio | G52: Implementação | H52: Criar harness de desempenho | I52: Medir startup interativo, ack IPC, latência de busca e frame times. | J52: tooling/bench/ | K52: Dados brutos incluem hardware, versão, dataset, warm/cold e repetição; não apenas médias soltas. | L52: SL-S05-06 | M52: R01; R09; R12; R15; R20; R34 | N52: Não iniciado | O52: P1 | P52: Alto | Q52: Obrigatória no escopo da versão | R52: Autor + agente de IA | U52: reports/S05/SL-S05-07.md | X52: =IF(N52="Concluído",IF(AND(S52<>"",ISNUMBER(T52),T52>0,V52<>"",AND(OR(X51="OK",X51="DISPENSADO"))),"OK","REVISAR"),IF(N52="Dispensado (ADR)",IF(AND(LEFT(Q52,11)="Condicional",W52<>"",S52<>"",ISNUMBER(T52),T52>0,V52<>""),"DISPENSADO","REVISAR"),"PENDENTE"))
A53: 52 | B53: SL-S05-08 | C53: v0.0.2 | D53: S05 | E53: Qualidade / desempenho | F53: Próprio | G53: Teste | H53: Gerar cenas sintéticas | I53: Criar boards de 100 e 1.000 nós com textos, imagens, grupos e conexões. | J53: tests/fixtures/boards/ | K53: Cenas são determinísticas e não representam só caixas vazias favoráveis ao benchmark. | L53: SL-S05-07 | M53: R01; R09; R12; R15; R20; R34 | N53: Não iniciado | O53: P1 | P53: Alto | Q53: Obrigatória no escopo da versão | R53: Autor + agente de IA | U53: reports/S05/SL-S05-08.md | X53: =IF(N53="Concluído",IF(AND(S53<>"",ISNUMBER(T53),T53>0,V53<>"",AND(OR(X52="OK",X52="DISPENSADO"))),"OK","REVISAR"),IF(N53="Dispensado (ADR)",IF(AND(LEFT(Q53,11)="Condicional",W53<>"",S53<>"",ISNUMBER(T53),T53>0,V53<>""),"DISPENSADO","REVISAR"),"PENDENTE"))
A54: 53 | B54: SL-S05-09 | C54: v0.0.2 | D54: S05 | E54: Qualidade / desempenho | F54: Próprio | G54: Implementação | H54: Padronizar evidências | I54: Definir JSON de resultados e caminho por tarefa, hash de commit e ambiente. | J54: schemas/evidence-report.json | K54: Relatório distingue executado, falhou, bloqueado e não executado; campo de aprovação é humano. | L54: SL-S05-08 | M54: R01; R09; R12; R15; R20; R34 | N54: Não iniciado | O54: P1 | P54: Alto | Q54: Obrigatória no escopo da versão | R54: Autor + agente de IA | U54: reports/S05/SL-S05-09.md | X54: =IF(N54="Concluído",IF(AND(S54<>"",ISNUMBER(T54),T54>0,V54<>"",AND(OR(X53="OK",X53="DISPENSADO"))),"OK","REVISAR"),IF(N54="Dispensado (ADR)",IF(AND(LEFT(Q54,11)="Condicional",W54<>"",S54<>"",ISNUMBER(T54),T54>0,V54<>""),"DISPENSADO","REVISAR"),"PENDENTE"))
A55: 54 | B55: SL-S05-10 | C55: v0.0.2 | D55: S05 | E55: Qualidade / desempenho | F55: Próprio | G55: Teste | H55: Validar a própria bancada | I55: Injetar regressão de tempo, erro de schema e ausência de runner. | J55: reports/ci-self-test.md | K55: Cada situação gera falha ou estado bloqueado, nunca resultado verde fictício. | L55: SL-S05-09 | M55: R01; R09; R12; R15; R20; R34 | N55: Não iniciado | O55: P1 | P55: Alto | Q55: Obrigatória no escopo da versão | R55: Autor + agente de IA | U55: reports/S05/SL-S05-10.md | X55: =IF(N55="Concluído",IF(AND(S55<>"",ISNUMBER(T55),T55>0,V55<>"",AND(OR(X54="OK",X54="DISPENSADO"))),"OK","REVISAR"),IF(N55="Dispensado (ADR)",IF(AND(LEFT(Q55,11)="Condicional",W55<>"",S55<>"",ISNUMBER(T55),T55>0,V55<>""),"DISPENSADO","REVISAR"),"PENDENTE"))
A56: 55 | B56: SL-S05-GATE | C56: v0.0.2 | D56: S05 | E56: Qualidade / desempenho | F56: Aceite humano | G56: Gate | H56: Aceitar S05 — Construir CI, corpus e protocolo de medição | I56: Revisar as dez tarefas, executar a demonstração do sprint, confrontar critérios e registrar decisão go/no-go. | J56: reports/S05/acceptance.md | K56: Falha introduzida em contrato bloqueia pipeline e um benchmark gera dados reproduzíveis. Todas as dependências aceitas; evidências vinculadas a revisão/ambiente; nenhum blocker de integridade/segurança. | L56: SL-S05-01; SL-S05-02; SL-S05-03; SL-S05-04; SL-S05-05; SL-S05-06; SL-S05-07; SL-S05-08; SL-S05-09; SL-S05-10 | M56: R01; R09; R12; R15; R20; R34 | N56: Não iniciado | O56: P0 | P56: Alto | Q56: Obrigatória para fechar a versão aprovada | R56: Autor | U56: reports/S05/acceptance.md | X56: =IF(N56="Concluído",IF(AND(S56<>"",ISNUMBER(T56),T56>0,V56<>"",AND(OR(X46="OK",X46="DISPENSADO"),OR(X47="OK",X47="DISPENSADO"),OR(X48="OK",X48="DISPENSADO"),OR(X49="OK",X49="DISPENSADO"),OR(X50="OK",X50="DISPENSADO"),OR(X51="OK",X51="DISPENSADO"),OR(X52="OK",X52="DISPENSADO"),OR(X53="OK",X53="DISPENSADO"),OR(X54="OK",X54="DISPENSADO"),OR(X55="OK",X55="DISPENSADO"))),"OK","REVISAR"),IF(N56="Dispensado (ADR)",IF(AND(LEFT(Q56,11)="Condicional",W56<>"",S56<>"",ISNUMBER(T56),T56>0,V56<>""),"DISPENSADO","REVISAR"),"PENDENTE"))
A57: 56 | B57: SL-S06-01 | C57: v0.0.2 | D57: S06 | E57: Tauri / apresentação | F57: Integração | G57: Implementação | H57: Inicializar Tauri v2 | I57: Montar frontend mínimo e Core; manter motores pesados fora do startup. | J57: apps/desktop/ | K57: Shell abre sem modelos, browsers, servidores de pesquisa ou bibliotecas Python carregados. | L57: SL-S04-GATE; SL-S05-GATE | M57: R01; R03; R07; R08; R31; R34 | N57: Não iniciado | O57: P0 | P57: Crítico | Q57: Obrigatória no escopo da versão | R57: Autor + agente de IA | U57: reports/S06/SL-S06-01.md | X57: =IF(N57="Concluído",IF(AND(S57<>"",ISNUMBER(T57),T57>0,V57<>"",AND(OR(X45="OK",X45="DISPENSADO"),OR(X56="OK",X56="DISPENSADO"))),"OK","REVISAR"),IF(N57="Dispensado (ADR)",IF(AND(LEFT(Q57,11)="Condicional",W57<>"",S57<>"",ISNUMBER(T57),T57>0,V57<>""),"DISPENSADO","REVISAR"),"PENDENTE"))
A58: 57 | B58: SL-S06-02 | C58: v0.0.2 | D58: S06 | E58: Tauri / apresentação | F58: Integração | G58: Implementação | H58: Definir contratos IPC | I58: Versionar request/response, erros, IDs e cancelamento; gerar tipos onde possível. | J58: schemas/ipc-v0.json | K58: Frontend não chama comandos arbitrários ou APIs nativas por nomes não autorizados. | L58: SL-S06-01 | M58: R01; R03; R07; R08; R31; R34 | N58: Não iniciado | O58: P0 | P58: Crítico | Q58: Obrigatória no escopo da versão | R58: Autor + agente de IA | U58: reports/S06/SL-S06-02.md | X58: =IF(N58="Concluído",IF(AND(S58<>"",ISNUMBER(T58),T58>0,V58<>"",AND(OR(X57="OK",X57="DISPENSADO"))),"OK","REVISAR"),IF(N58="Dispensado (ADR)",IF(AND(LEFT(Q58,11)="Condicional",W58<>"",S58<>"",ISNUMBER(T58),T58>0,V58<>""),"DISPENSADO","REVISAR"),"PENDENTE"))
A59: 58 | B59: SL-S06-03 | C59: v0.0.2 | D59: S06 | E59: Tauri / apresentação | F59: Integração | G59: Implementação | H59: Configurar capabilities | I59: Expor apenas comandos do app e aplicar CSP restritiva à apresentação. | J59: apps/desktop/capabilities/ | K59: Script de conteúdo não obtém acesso automático a filesystem, shell ou segredos. | L59: SL-S06-02 | M59: R01; R03; R07; R08; R31; R34 | N59: Não iniciado | O59: P0 | P59: Crítico | Q59: Obrigatória no escopo da versão | R59: Autor + agente de IA | U59: reports/S06/SL-S06-03.md | X59: =IF(N59="Concluído",IF(AND(S59<>"",ISNUMBER(T59),T59>0,V59<>"",AND(OR(X58="OK",X58="DISPENSADO"))),"OK","REVISAR"),IF(N59="Dispensado (ADR)",IF(AND(LEFT(Q59,11)="Condicional",W59<>"",S59<>"",ISNUMBER(T59),T59>0,V59<>""),"DISPENSADO","REVISAR"),"PENDENTE"))
A60: 59 | B60: SL-S06-04 | C60: v0.0.2 | D60: S06 | E60: Tauri / apresentação | F60: Integração | G60: Implementação | H60: Montar navegação de fases | I60: Criar estados Ingest, Mesa, Peça e ajustes sem duplicar dados por tela. | J60: apps/desktop/src/shell/ | K60: Alternar fase não perde estado nem exige conta ou serviço remoto. | L60: SL-S06-03 | M60: R01; R03; R07; R08; R31; R34 | N60: Não iniciado | O60: P0 | P60: Crítico | Q60: Obrigatória no escopo da versão | R60: Autor + agente de IA | U60: reports/S06/SL-S06-04.md | X60: =IF(N60="Concluído",IF(AND(S60<>"",ISNUMBER(T60),T60>0,V60<>"",AND(OR(X59="OK",X59="DISPENSADO"))),"OK","REVISAR"),IF(N60="Dispensado (ADR)",IF(AND(LEFT(Q60,11)="Condicional",W60<>"",S60<>"",ISNUMBER(T60),T60>0,V60<>""),"DISPENSADO","REVISAR"),"PENDENTE"))
A61: 60 | B61: SL-S06-05 | C61: v0.0.2 | D61: S06 | E61: Tauri / apresentação | F61: Integração | G61: Implementação | H61: Implementar seleção de Vault | I61: Usar diálogo nativo e raiz dinâmica; adiar leitura ao serviço autorizado. | J61: crates/app-core/src/vault_selection.rs | K61: Paths com espaços/Unicode funcionam e nenhuma raiz de usuário está hardcoded. | L61: SL-S06-04 | M61: R01; R03; R07; R08; R31; R34 | N61: Não iniciado | O61: P0 | P61: Crítico | Q61: Obrigatória no escopo da versão | R61: Autor + agente de IA | U61: reports/S06/SL-S06-05.md | X61: =IF(N61="Concluído",IF(AND(S61<>"",ISNUMBER(T61),T61>0,V61<>"",AND(OR(X60="OK",X60="DISPENSADO"))),"OK","REVISAR"),IF(N61="Dispensado (ADR)",IF(AND(LEFT(Q61,11)="Condicional",W61<>"",S61<>"",ISNUMBER(T61),T61>0,V61<>""),"DISPENSADO","REVISAR"),"PENDENTE"))
A62: 61 | B62: SL-S06-06 | C62: v0.0.2 | D62: S06 | E62: Tauri / apresentação | F62: Integração | G62: Implementação | H62: Criar estados de tarefa | I62: Padronizar vazio, carregando, falhou, bloqueado, offline e concluído. | J62: apps/desktop/src/components/status/ | K62: Falha recuperável mostra ação útil e não fica em spinner infinito. | L62: SL-S06-05 | M62: R01; R03; R07; R08; R31; R34 | N62: Não iniciado | O62: P0 | P62: Crítico | Q62: Obrigatória no escopo da versão | R62: Autor + agente de IA | U62: reports/S06/SL-S06-06.md | X62: =IF(N62="Concluído",IF(AND(S62<>"",ISNUMBER(T62),T62>0,V62<>"",AND(OR(X61="OK",X61="DISPENSADO"))),"OK","REVISAR"),IF(N62="Dispensado (ADR)",IF(AND(LEFT(Q62,11)="Condicional",W62<>"",S62<>"",ISNUMBER(T62),T62>0,V62<>""),"DISPENSADO","REVISAR"),"PENDENTE"))
A63: 62 | B63: SL-S06-07 | C63: v0.0.2 | D63: S06 | E63: Tauri / apresentação | F63: Integração | G63: Implementação | H63: Preparar acessibilidade básica | I63: Dar nomes, foco e atalhos às regiões principais. | J63: apps/desktop/src/accessibility/ | K63: Percurso essencial por teclado funciona sem mouse; foco não desaparece ao trocar de fase. | L63: SL-S06-06 | M63: R01; R03; R07; R08; R31; R34 | N63: Não iniciado | O63: P0 | P63: Crítico | Q63: Obrigatória no escopo da versão | R63: Autor + agente de IA | U63: reports/S06/SL-S06-07.md | X63: =IF(N63="Concluído",IF(AND(S63<>"",ISNUMBER(T63),T63>0,V63<>"",AND(OR(X62="OK",X62="DISPENSADO"))),"OK","REVISAR"),IF(N63="Dispensado (ADR)",IF(AND(LEFT(Q63,11)="Condicional",W63<>"",S63<>"",ISNUMBER(T63),T63>0,V63<>""),"DISPENSADO","REVISAR"),"PENDENTE"))
A64: 63 | B64: SL-S06-08 | C64: v0.0.2 | D64: S06 | E64: Tauri / apresentação | F64: Integração | G64: Implementação | H64: Integrar logs locais saneados | I64: Emitir IDs e tempos sem incluir texto do Vault por padrão. | J64: crates/diagnostics/ | K64: Fixture sensível não aparece em log, erro serializado ou console da UI. | L64: SL-S06-07 | M64: R01; R03; R07; R08; R31; R34 | N64: Não iniciado | O64: P0 | P64: Crítico | Q64: Obrigatória no escopo da versão | R64: Autor + agente de IA | U64: reports/S06/SL-S06-08.md | X64: =IF(N64="Concluído",IF(AND(S64<>"",ISNUMBER(T64),T64>0,V64<>"",AND(OR(X63="OK",X63="DISPENSADO"))),"OK","REVISAR"),IF(N64="Dispensado (ADR)",IF(AND(LEFT(Q64,11)="Condicional",W64<>"",S64<>"",ISNUMBER(T64),T64>0,V64<>""),"DISPENSADO","REVISAR"),"PENDENTE"))
A65: 64 | B65: SL-S06-09 | C65: v0.0.2 | D65: S06 | E65: Tauri / apresentação | F65: Integração | G65: Teste | H65: Fazer smoke nos alvos disponíveis | I65: Abrir/fechar, selecionar pasta e testar IPC em ambientes reais. | J65: reports/shell-targets/ | K65: Ambiente não disponível é marcado bloqueado, com tarefa de acesso antes da homologação. | L65: SL-S06-08 | M65: R01; R03; R07; R08; R31; R34 | N65: Não iniciado | O65: P0 | P65: Crítico | Q65: Obrigatória no escopo da versão | R65: Autor + agente de IA | U65: reports/S06/SL-S06-09.md | X65: =IF(N65="Concluído",IF(AND(S65<>"",ISNUMBER(T65),T65>0,V65<>"",AND(OR(X64="OK",X64="DISPENSADO"))),"OK","REVISAR"),IF(N65="Dispensado (ADR)",IF(AND(LEFT(Q65,11)="Condicional",W65<>"",S65<>"",ISNUMBER(T65),T65>0,V65<>""),"DISPENSADO","REVISAR"),"PENDENTE"))
A66: 65 | B66: SL-S06-10 | C66: v0.0.2 | D66: S06 | E66: Tauri / apresentação | F66: Integração | G66: Teste | H66: Medir baseline vazio | I66: Registrar árvore de processos e startup sem funcionalidades opcionais. | J66: reports/baseline-shell.json | K66: Baseline reproduzível permite atribuir consumo incremental a motores futuros. | L66: SL-S06-09 | M66: R01; R03; R07; R08; R31; R34 | N66: Não iniciado | O66: P0 | P66: Crítico | Q66: Obrigatória no escopo da versão | R66: Autor + agente de IA | U66: reports/S06/SL-S06-10.md | X66: =IF(N66="Concluído",IF(AND(S66<>"",ISNUMBER(T66),T66>0,V66<>"",AND(OR(X65="OK",X65="DISPENSADO"))),"OK","REVISAR"),IF(N66="Dispensado (ADR)",IF(AND(LEFT(Q66,11)="Condicional",W66<>"",S66<>"",ISNUMBER(T66),T66>0,V66<>""),"DISPENSADO","REVISAR"),"PENDENTE"))
A67: 66 | B67: SL-S06-GATE | C67: v0.0.2 | D67: S06 | E67: Tauri / apresentação | F67: Aceite humano | G67: Gate | H67: Aceitar S06 — Criar shell desktop e contratos IPC | I67: Revisar as dez tarefas, executar a demonstração do sprint, confrontar critérios e registrar decisão go/no-go. | J67: reports/S06/acceptance.md | K67: Instalar build de desenvolvimento, navegar e selecionar um diretório sem rede. Todas as dependências aceitas; evidências vinculadas a revisão/ambiente; nenhum blocker de integridade/segurança. | L67: SL-S06-01; SL-S06-02; SL-S06-03; SL-S06-04; SL-S06-05; SL-S06-06; SL-S06-07; SL-S06-08; SL-S06-09; SL-S06-10 | M67: R01; R03; R07; R08; R31; R34 | N67: Não iniciado | O67: P0 | P67: Crítico | Q67: Obrigatória para fechar a versão aprovada | R67: Autor | U67: reports/S06/acceptance.md | X67: =IF(N67="Concluído",IF(AND(S67<>"",ISNUMBER(T67),T67>0,V67<>"",AND(OR(X57="OK",X57="DISPENSADO"),OR(X58="OK",X58="DISPENSADO"),OR(X59="OK",X59="DISPENSADO"),OR(X60="OK",X60="DISPENSADO"),OR(X61="OK",X61="DISPENSADO"),OR(X62="OK",X62="DISPENSADO"),OR(X63="OK",X63="DISPENSADO"),OR(X64="OK",X64="DISPENSADO"),OR(X65="OK",X65="DISPENSADO"),OR(X66="OK",X66="DISPENSADO"))),"OK","REVISAR"),IF(N67="Dispensado (ADR)",IF(AND(LEFT(Q67,11)="Condicional",W67<>"",S67<>"",ISNUMBER(T67),T67>0,V67<>""),"DISPENSADO","REVISAR"),"PENDENTE"))
A68: 67 | B68: SL-S07-01 | C68: v0.1.0 | D68: S07 | E68: VaultStore / CAS | F68: Próprio | G68: Implementação | H68: Criar lifecycle do Vault | I68: Abrir, criar, validar versão e recusar raiz inválida sem modificar seus arquivos. | J68: crates/vault/src/lifecycle.rs | K68: Pasta existente incompatível não é sobrescrita; erro aponta a causa. | L68: SL-S02-GATE; SL-S06-GATE | M68: R02; R04; R05; R07 | N68: Não iniciado | O68: P0 | P68: Crítico | Q68: Obrigatória no escopo da versão | R68: Autor + agente de IA | U68: reports/S07/SL-S07-01.md | X68: =IF(N68="Concluído",IF(AND(S68<>"",ISNUMBER(T68),T68>0,V68<>"",AND(OR(X23="OK",X23="DISPENSADO"),OR(X67="OK",X67="DISPENSADO"))),"OK","REVISAR"),IF(N68="Dispensado (ADR)",IF(AND(LEFT(Q68,11)="Condicional",W68<>"",S68<>"",ISNUMBER(T68),T68>0,V68<>""),"DISPENSADO","REVISAR"),"PENDENTE"))
A69: 68 | B69: SL-S07-02 | C69: v0.1.0 | D69: S07 | E69: VaultStore / CAS | F69: Próprio | G69: Implementação | H69: Implementar identidade | I69: Gerar IDs, detectar duplicatas e separar ID de localização atual. | J69: crates/domain/src/identity.rs | K69: Renomear não muda ID; cópia com ID repetido gera conflito tratável. | L69: SL-S07-01 | M69: R02; R04; R05; R07 | N69: Não iniciado | O69: P0 | P69: Crítico | Q69: Obrigatória no escopo da versão | R69: Autor + agente de IA | U69: reports/S07/SL-S07-02.md | X69: =IF(N69="Concluído",IF(AND(S69<>"",ISNUMBER(T69),T69>0,V69<>"",AND(OR(X68="OK",X68="DISPENSADO"))),"OK","REVISAR"),IF(N69="Dispensado (ADR)",IF(AND(LEFT(Q69,11)="Condicional",W69<>"",S69<>"",ISNUMBER(T69),T69>0,V69<>""),"DISPENSADO","REVISAR"),"PENDENTE"))
A70: 69 | B70: SL-S07-03 | C70: v0.1.0 | D70: S07 | E70: VaultStore / CAS | F70: Próprio | G70: Implementação | H70: Ler/escrever frontmatter | I70: Preservar campos desconhecidos e tipos permitidos no perfil aprovado. | J70: crates/vault/src/markdown.rs | K70: Round-trip de fixtures não apaga extensões nem converte datas/strings inadvertidamente. | L70: SL-S07-02 | M70: R02; R04; R05; R07 | N70: Não iniciado | O70: P0 | P70: Crítico | Q70: Obrigatória no escopo da versão | R70: Autor + agente de IA | U70: reports/S07/SL-S07-03.md | X70: =IF(N70="Concluído",IF(AND(S70<>"",ISNUMBER(T70),T70>0,V70<>"",AND(OR(X69="OK",X69="DISPENSADO"))),"OK","REVISAR"),IF(N70="Dispensado (ADR)",IF(AND(LEFT(Q70,11)="Condicional",W70<>"",S70<>"",ISNUMBER(T70),T70>0,V70<>""),"DISPENSADO","REVISAR"),"PENDENTE"))
A71: 70 | B71: SL-S07-04 | C71: v0.1.0 | D71: S07 | E71: VaultStore / CAS | F71: Próprio | G71: Implementação | H71: Implementar CAS | I71: Calcular hash por streaming, detectar duplicatas e publicar arquivo completo. | J71: crates/vault/src/assets.rs | K71: Dois imports iguais compartilham bytes; interrupção não cria asset final parcial. | L71: SL-S07-03 | M71: R02; R04; R05; R07 | N71: Não iniciado | O71: P0 | P71: Crítico | Q71: Obrigatória no escopo da versão | R71: Autor + agente de IA | U71: reports/S07/SL-S07-04.md | X71: =IF(N71="Concluído",IF(AND(S71<>"",ISNUMBER(T71),T71>0,V71<>"",AND(OR(X70="OK",X70="DISPENSADO"))),"OK","REVISAR"),IF(N71="Dispensado (ADR)",IF(AND(LEFT(Q71,11)="Condicional",W71<>"",S71<>"",ISNUMBER(T71),T71>0,V71<>""),"DISPENSADO","REVISAR"),"PENDENTE"))
A72: 71 | B72: SL-S07-05 | C72: v0.1.0 | D72: S07 | E72: VaultStore / CAS | F72: Próprio | G72: Implementação | H72: Mapear referências de assets | I72: Referenciar hash/tipo sem caminhos absolutos dependentes da máquina. | J72: crates/domain/src/asset_ref.rs | K72: Vault copiado para outra raiz continua resolvendo anexos. | L72: SL-S07-04 | M72: R02; R04; R05; R07 | N72: Não iniciado | O72: P0 | P72: Crítico | Q72: Obrigatória no escopo da versão | R72: Autor + agente de IA | U72: reports/S07/SL-S07-05.md | X72: =IF(N72="Concluído",IF(AND(S72<>"",ISNUMBER(T72),T72>0,V72<>"",AND(OR(X71="OK",X71="DISPENSADO"))),"OK","REVISAR"),IF(N72="Dispensado (ADR)",IF(AND(LEFT(Q72,11)="Condicional",W72<>"",S72<>"",ISNUMBER(T72),T72>0,V72<>""),"DISPENSADO","REVISAR"),"PENDENTE"))
A73: 72 | B73: SL-S07-06 | C73: v0.1.0 | D73: S07 | E73: VaultStore / CAS | F73: Próprio | G73: Implementação | H73: Criar workspace/célula | I73: Persistir manifest, board vazio e célula Markdown por contratos. | J73: crates/vault/src/workspaces.rs | K73: Criação incompleta é detectada e reparável sem gerar workspace invisível perdido. | L73: SL-S07-05 | M73: R02; R04; R05; R07 | N73: Não iniciado | O73: P0 | P73: Crítico | Q73: Obrigatória no escopo da versão | R73: Autor + agente de IA | U73: reports/S07/SL-S07-06.md | X73: =IF(N73="Concluído",IF(AND(S73<>"",ISNUMBER(T73),T73>0,V73<>"",AND(OR(X72="OK",X72="DISPENSADO"))),"OK","REVISAR"),IF(N73="Dispensado (ADR)",IF(AND(LEFT(Q73,11)="Condicional",W73<>"",S73<>"",ISNUMBER(T73),T73>0,V73<>""),"DISPENSADO","REVISAR"),"PENDENTE"))
A74: 73 | B74: SL-S07-07 | C74: v0.1.0 | D74: S07 | E74: VaultStore / CAS | F74: Próprio | G74: Implementação | H74: Implementar inventário por varredura | I74: Ler arquivos canônicos sem exigir banco existente. | J74: crates/vault/src/scan.rs | K74: Inventário inicial retorna os mesmos IDs após remover índices derivados. | L74: SL-S07-06 | M74: R02; R04; R05; R07 | N74: Não iniciado | O74: P0 | P74: Crítico | Q74: Obrigatória no escopo da versão | R74: Autor + agente de IA | U74: reports/S07/SL-S07-07.md | X74: =IF(N74="Concluído",IF(AND(S74<>"",ISNUMBER(T74),T74>0,V74<>"",AND(OR(X73="OK",X73="DISPENSADO"))),"OK","REVISAR"),IF(N74="Dispensado (ADR)",IF(AND(LEFT(Q74,11)="Condicional",W74<>"",S74<>"",ISNUMBER(T74),T74>0,V74<>""),"DISPENSADO","REVISAR"),"PENDENTE"))
A75: 74 | B75: SL-S07-08 | C75: v0.1.0 | D75: S07 | E75: VaultStore / CAS | F75: Próprio | G75: Implementação | H75: Definir descarte e recuperação | I75: Criar lixeira/tombstones sem destruir imediatamente a fonte de rollback. | J75: crates/vault/src/deletion.rs | K75: Excluir uma referência não apaga asset ainda usado por outra célula ou revisão. | L75: SL-S07-07 | M75: R02; R04; R05; R07 | N75: Não iniciado | O75: P0 | P75: Crítico | Q75: Obrigatória no escopo da versão | R75: Autor + agente de IA | U75: reports/S07/SL-S07-08.md | X75: =IF(N75="Concluído",IF(AND(S75<>"",ISNUMBER(T75),T75>0,V75<>"",AND(OR(X74="OK",X74="DISPENSADO"))),"OK","REVISAR"),IF(N75="Dispensado (ADR)",IF(AND(LEFT(Q75,11)="Condicional",W75<>"",S75<>"",ISNUMBER(T75),T75>0,V75<>""),"DISPENSADO","REVISAR"),"PENDENTE"))
A76: 75 | B76: SL-S07-09 | C76: v0.1.0 | D76: S07 | E76: VaultStore / CAS | F76: Próprio | G76: Teste | H76: Testar portabilidade de paths | I76: Cobrir Unicode, case sensitivity, nomes reservados e diretórios longos. | J76: tests/vault/path-compat/ | K76: Casos não suportados são recusados com explicação em vez de truncados silenciosamente. | L76: SL-S07-08 | M76: R02; R04; R05; R07 | N76: Não iniciado | O76: P0 | P76: Crítico | Q76: Obrigatória no escopo da versão | R76: Autor + agente de IA | U76: reports/S07/SL-S07-09.md | X76: =IF(N76="Concluído",IF(AND(S76<>"",ISNUMBER(T76),T76>0,V76<>"",AND(OR(X75="OK",X75="DISPENSADO"))),"OK","REVISAR"),IF(N76="Dispensado (ADR)",IF(AND(LEFT(Q76,11)="Condicional",W76<>"",S76<>"",ISNUMBER(T76),T76>0,V76<>""),"DISPENSADO","REVISAR"),"PENDENTE"))
A77: 76 | B77: SL-S07-10 | C77: v0.1.0 | D77: S07 | E77: VaultStore / CAS | F77: Próprio | G77: Teste | H77: Criar ferramenta de inspeção | I77: Listar invariantes e problemas em modo somente leitura. | J77: tooling/vault-inspect/ | K77: Ferramenta lê o Vault sem iniciar UI, modelos ou serviços externos. | L77: SL-S07-09 | M77: R02; R04; R05; R07 | N77: Não iniciado | O77: P0 | P77: Crítico | Q77: Obrigatória no escopo da versão | R77: Autor + agente de IA | U77: reports/S07/SL-S07-10.md | X77: =IF(N77="Concluído",IF(AND(S77<>"",ISNUMBER(T77),T77>0,V77<>"",AND(OR(X76="OK",X76="DISPENSADO"))),"OK","REVISAR"),IF(N77="Dispensado (ADR)",IF(AND(LEFT(Q77,11)="Condicional",W77<>"",S77<>"",ISNUMBER(T77),T77>0,V77<>""),"DISPENSADO","REVISAR"),"PENDENTE"))
A78: 77 | B78: SL-S07-GATE | C78: v0.1.0 | D78: S07 | E78: VaultStore / CAS | F78: Aceite humano | G78: Gate | H78: Aceitar S07 — Implementar Vault, identidade e assets | I78: Revisar as dez tarefas, executar a demonstração do sprint, confrontar critérios e registrar decisão go/no-go. | J78: reports/S07/acceptance.md | K78: Criar Vault, salvar nota/asset, fechar e listar os mesmos IDs ao reabrir. Todas as dependências aceitas; evidências vinculadas a revisão/ambiente; nenhum blocker de integridade/segurança. | L78: SL-S07-01; SL-S07-02; SL-S07-03; SL-S07-04; SL-S07-05; SL-S07-06; SL-S07-07; SL-S07-08; SL-S07-09; SL-S07-10 | M78: R02; R04; R05; R07 | N78: Não iniciado | O78: P0 | P78: Crítico | Q78: Obrigatória para fechar a versão aprovada | R78: Autor | U78: reports/S07/acceptance.md | X78: =IF(N78="Concluído",IF(AND(S78<>"",ISNUMBER(T78),T78>0,V78<>"",AND(OR(X68="OK",X68="DISPENSADO"),OR(X69="OK",X69="DISPENSADO"),OR(X70="OK",X70="DISPENSADO"),OR(X71="OK",X71="DISPENSADO"),OR(X72="OK",X72="DISPENSADO"),OR(X73="OK",X73="DISPENSADO"),OR(X74="OK",X74="DISPENSADO"),OR(X75="OK",X75="DISPENSADO"),OR(X76="OK",X76="DISPENSADO"),OR(X77="OK",X77="DISPENSADO"))),"OK","REVISAR"),IF(N78="Dispensado (ADR)",IF(AND(LEFT(Q78,11)="Condicional",W78<>"",S78<>"",ISNUMBER(T78),T78>0,V78<>""),"DISPENSADO","REVISAR"),"PENDENTE"))
A79: 78 | B79: SL-S08-01 | C79: v0.1.0 | D79: S08 | E79: Journal / RevisionStore | F79: Próprio | G79: Contrato | H79: Especificar máquina de estados de commit | I79: Definir preparação, confirmação, publicação e replay idempotente. | J79: docs/contracts/file-commit.md | K79: Ordem de flush/rename e estado reconhecido após cada falha estão definidos por SO. | L79: SL-S07-GATE | M79: R02; R05; R13; R37 | N79: Não iniciado | O79: P0 | P79: Crítico | Q79: Obrigatória no escopo da versão | R79: Autor + agente de IA | U79: reports/S08/SL-S08-01.md | X79: =IF(N79="Concluído",IF(AND(S79<>"",ISNUMBER(T79),T79>0,V79<>"",AND(OR(X78="OK",X78="DISPENSADO"))),"OK","REVISAR"),IF(N79="Dispensado (ADR)",IF(AND(LEFT(Q79,11)="Condicional",W79<>"",S79<>"",ISNUMBER(T79),T79>0,V79<>""),"DISPENSADO","REVISAR"),"PENDENTE"))
A80: 79 | B80: SL-S08-02 | C80: v0.1.0 | D80: S08 | E80: Journal / RevisionStore | F80: Próprio | G80: Implementação | H80: Criar escritor único | I80: Serializar mutações por Vault e validar expected_revision. | J80: crates/vault/src/writer.rs | K80: Duas edições concorrentes não substituem uma à outra sem conflito explícito. | L80: SL-S08-01 | M80: R02; R05; R13; R37 | N80: Não iniciado | O80: P0 | P80: Crítico | Q80: Obrigatória no escopo da versão | R80: Autor + agente de IA | U80: reports/S08/SL-S08-02.md | X80: =IF(N80="Concluído",IF(AND(S80<>"",ISNUMBER(T80),T80>0,V80<>"",AND(OR(X79="OK",X79="DISPENSADO"))),"OK","REVISAR"),IF(N80="Dispensado (ADR)",IF(AND(LEFT(Q80,11)="Condicional",W80<>"",S80<>"",ISNUMBER(T80),T80>0,V80<>""),"DISPENSADO","REVISAR"),"PENDENTE"))
A81: 80 | B81: SL-S08-03 | C81: v0.1.0 | D81: S08 | E81: Journal / RevisionStore | F81: Próprio | G81: Implementação | H81: Persistir objetos de revisão | I81: Armazenar snapshots/deltas necessários antes de anunciar commit. | J81: crates/history/src/objects.rs | K81: Toda revisão confirmada possui objetos íntegros para reconstrução. | L81: SL-S08-02 | M81: R02; R05; R13; R37 | N81: Não iniciado | O81: P0 | P81: Crítico | Q81: Obrigatória no escopo da versão | R81: Autor + agente de IA | U81: reports/S08/SL-S08-03.md | X81: =IF(N81="Concluído",IF(AND(S81<>"",ISNUMBER(T81),T81>0,V81<>"",AND(OR(X80="OK",X80="DISPENSADO"))),"OK","REVISAR"),IF(N81="Dispensado (ADR)",IF(AND(LEFT(Q81,11)="Condicional",W81<>"",S81<>"",ISNUMBER(T81),T81>0,V81<>""),"DISPENSADO","REVISAR"),"PENDENTE"))
A82: 81 | B82: SL-S08-04 | C82: v0.1.0 | D82: S08 | E82: Journal / RevisionStore | F82: Próprio | G82: Implementação | H82: Implementar journal | I82: Registrar eventos, integridade de registros e tratamento de cauda truncada. | J82: crates/history/src/journal.rs | K82: Registro parcial não invalida commits anteriores e não é executado como completo. | L82: SL-S08-03 | M82: R02; R05; R13; R37 | N82: Não iniciado | O82: P0 | P82: Crítico | Q82: Obrigatória no escopo da versão | R82: Autor + agente de IA | U82: reports/S08/SL-S08-04.md | X82: =IF(N82="Concluído",IF(AND(S82<>"",ISNUMBER(T82),T82>0,V82<>"",AND(OR(X81="OK",X81="DISPENSADO"))),"OK","REVISAR"),IF(N82="Dispensado (ADR)",IF(AND(LEFT(Q82,11)="Condicional",W82<>"",S82<>"",ISNUMBER(T82),T82>0,V82<>""),"DISPENSADO","REVISAR"),"PENDENTE"))
A83: 82 | B83: SL-S08-05 | C83: v0.1.0 | D83: S08 | E83: Journal / RevisionStore | F83: Próprio | G83: Implementação | H83: Publicar arquivos atômicos | I83: Usar temporários, flush e troca apropriada; documentar garantias reais de cada SO. | J83: crates/vault/src/atomic_write.rs | K83: Leitor observa versão anterior ou nova completa; falhas de disco são propagadas. | L83: SL-S08-04 | M83: R02; R05; R13; R37 | N83: Não iniciado | O83: P0 | P83: Crítico | Q83: Obrigatória no escopo da versão | R83: Autor + agente de IA | U83: reports/S08/SL-S08-05.md | X83: =IF(N83="Concluído",IF(AND(S83<>"",ISNUMBER(T83),T83>0,V83<>"",AND(OR(X82="OK",X82="DISPENSADO"))),"OK","REVISAR"),IF(N83="Dispensado (ADR)",IF(AND(LEFT(Q83,11)="Condicional",W83<>"",S83<>"",ISNUMBER(T83),T83>0,V83<>""),"DISPENSADO","REVISAR"),"PENDENTE"))
A84: 83 | B84: SL-S08-06 | C84: v0.1.0 | D84: S08 | E84: Journal / RevisionStore | F84: Próprio | G84: Implementação | H84: Implementar replay | I84: Repetir operações confirmadas sem criar cópias ou efeitos extras. | J84: crates/history/src/replay.rs | K84: Executar replay duas vezes produz o mesmo estado e contagem de entidades. | L84: SL-S08-05 | M84: R02; R05; R13; R37 | N84: Não iniciado | O84: P0 | P84: Crítico | Q84: Obrigatória no escopo da versão | R84: Autor + agente de IA | U84: reports/S08/SL-S08-06.md | X84: =IF(N84="Concluído",IF(AND(S84<>"",ISNUMBER(T84),T84>0,V84<>"",AND(OR(X83="OK",X83="DISPENSADO"))),"OK","REVISAR"),IF(N84="Dispensado (ADR)",IF(AND(LEFT(Q84,11)="Condicional",W84<>"",S84<>"",ISNUMBER(T84),T84>0,V84<>""),"DISPENSADO","REVISAR"),"PENDENTE"))
A85: 84 | B85: SL-S08-07 | C85: v0.1.0 | D85: S08 | E85: Journal / RevisionStore | F85: Próprio | G85: Implementação | H85: Criar undo semântico | I85: Reverter edição, tag ou operação de board por nova operação registrada. | J85: crates/history/src/undo.rs | K85: Undo preserva proveniência e não apaga a existência do evento original. | L85: SL-S08-06 | M85: R02; R05; R13; R37 | N85: Não iniciado | O85: P0 | P85: Crítico | Q85: Obrigatória no escopo da versão | R85: Autor + agente de IA | U85: reports/S08/SL-S08-07.md | X85: =IF(N85="Concluído",IF(AND(S85<>"",ISNUMBER(T85),T85>0,V85<>"",AND(OR(X84="OK",X84="DISPENSADO"))),"OK","REVISAR"),IF(N85="Dispensado (ADR)",IF(AND(LEFT(Q85,11)="Condicional",W85<>"",S85<>"",ISNUMBER(T85),T85>0,V85<>""),"DISPENSADO","REVISAR"),"PENDENTE"))
A86: 85 | B86: SL-S08-08 | C86: v0.1.0 | D86: S08 | E86: Journal / RevisionStore | F86: Próprio | G86: Implementação | H86: Encadear eventos | I86: Definir serialização canônica, hashes e verificação do histórico. | J86: crates/history/src/integrity.rs | K86: Alteração detectada relativamente ao checkpoint confiável; limite de reescrita total documentado. | L86: SL-S08-07 | M86: R02; R05; R13; R37 | N86: Não iniciado | O86: P0 | P86: Crítico | Q86: Obrigatória no escopo da versão | R86: Autor + agente de IA | U86: reports/S08/SL-S08-08.md | X86: =IF(N86="Concluído",IF(AND(S86<>"",ISNUMBER(T86),T86>0,V86<>"",AND(OR(X85="OK",X85="DISPENSADO"))),"OK","REVISAR"),IF(N86="Dispensado (ADR)",IF(AND(LEFT(Q86,11)="Condicional",W86<>"",S86<>"",ISNUMBER(T86),T86>0,V86<>""),"DISPENSADO","REVISAR"),"PENDENTE"))
A87: 86 | B87: SL-S08-09 | C87: v0.1.0 | D87: S08 | E87: Journal / RevisionStore | F87: Próprio | G87: Teste | H87: Injetar falhas de I/O | I87: Simular disco cheio, permissão, flush/rename interrompidos e erro de objeto ausente. | J87: tests/history/fault-injection/ | K87: App não informa salvo para commit não durável nem remove a única cópia válida. | L87: SL-S08-08 | M87: R02; R05; R13; R37 | N87: Não iniciado | O87: P0 | P87: Crítico | Q87: Obrigatória no escopo da versão | R87: Autor + agente de IA | U87: reports/S08/SL-S08-09.md | X87: =IF(N87="Concluído",IF(AND(S87<>"",ISNUMBER(T87),T87>0,V87<>"",AND(OR(X86="OK",X86="DISPENSADO"))),"OK","REVISAR"),IF(N87="Dispensado (ADR)",IF(AND(LEFT(Q87,11)="Condicional",W87<>"",S87<>"",ISNUMBER(T87),T87>0,V87<>""),"DISPENSADO","REVISAR"),"PENDENTE"))
A88: 87 | B88: SL-S08-10 | C88: v0.1.0 | D88: S08 | E88: Journal / RevisionStore | F88: Próprio | G88: Teste | H88: Medir janela de perda | I88: Instrumentar timestamps de edição/commit e executar encerramentos controlados. | J88: reports/durability-window.json | K88: Janela de 500 ms é medida; teste de processo não é apresentado como teste de queda de energia. | L88: SL-S08-09 | M88: R02; R05; R13; R37 | N88: Não iniciado | O88: P0 | P88: Crítico | Q88: Obrigatória no escopo da versão | R88: Autor + agente de IA | U88: reports/S08/SL-S08-10.md | X88: =IF(N88="Concluído",IF(AND(S88<>"",ISNUMBER(T88),T88>0,V88<>"",AND(OR(X87="OK",X87="DISPENSADO"))),"OK","REVISAR"),IF(N88="Dispensado (ADR)",IF(AND(LEFT(Q88,11)="Condicional",W88<>"",S88<>"",ISNUMBER(T88),T88>0,V88<>""),"DISPENSADO","REVISAR"),"PENDENTE"))
A89: 88 | B89: SL-S08-GATE | C89: v0.1.0 | D89: S08 | E89: Journal / RevisionStore | F89: Aceite humano | G89: Gate | H89: Aceitar S08 — Implementar transações de arquivos e histórico | I89: Revisar as dez tarefas, executar a demonstração do sprint, confrontar critérios e registrar decisão go/no-go. | J89: reports/S08/acceptance.md | K89: Interromper cada etapa de uma edição e recuperar o último estado confirmado. Todas as dependências aceitas; evidências vinculadas a revisão/ambiente; nenhum blocker de integridade/segurança. | L89: SL-S08-01; SL-S08-02; SL-S08-03; SL-S08-04; SL-S08-05; SL-S08-06; SL-S08-07; SL-S08-08; SL-S08-09; SL-S08-10 | M89: R02; R05; R13; R37 | N89: Não iniciado | O89: P0 | P89: Crítico | Q89: Obrigatória para fechar a versão aprovada | R89: Autor | U89: reports/S08/acceptance.md | X89: =IF(N89="Concluído",IF(AND(S89<>"",ISNUMBER(T89),T89>0,V89<>"",AND(OR(X79="OK",X79="DISPENSADO"),OR(X80="OK",X80="DISPENSADO"),OR(X81="OK",X81="DISPENSADO"),OR(X82="OK",X82="DISPENSADO"),OR(X83="OK",X83="DISPENSADO"),OR(X84="OK",X84="DISPENSADO"),OR(X85="OK",X85="DISPENSADO"),OR(X86="OK",X86="DISPENSADO"),OR(X87="OK",X87="DISPENSADO"),OR(X88="OK",X88="DISPENSADO"))),"OK","REVISAR"),IF(N89="Dispensado (ADR)",IF(AND(LEFT(Q89,11)="Condicional",W89<>"",S89<>"",ISNUMBER(T89),T89>0,V89<>""),"DISPENSADO","REVISAR"),"PENDENTE"))
A90: 89 | B90: SL-S09-01 | C90: v0.1.0 | D90: S09 | E90: VaultGuard / ToolBroker | F90: Próprio | G90: Contrato | H90: Definir capabilities de I/O | I90: Vincular ator, workspace, objetos permitidos, operação, expiração e revisão. | J90: schemas/io-capability.json | K90: Capacidade de leitura não autoriza escrita nem acesso a outro workspace. | L90: SL-S07-GATE; SL-S08-GATE | M90: R06; R08; R34 | N90: Não iniciado | O90: P0 | P90: Crítico | Q90: Obrigatória no escopo da versão | R90: Autor + agente de IA | U90: reports/S09/SL-S09-01.md | X90: =IF(N90="Concluído",IF(AND(S90<>"",ISNUMBER(T90),T90>0,V90<>"",AND(OR(X78="OK",X78="DISPENSADO"),OR(X89="OK",X89="DISPENSADO"))),"OK","REVISAR"),IF(N90="Dispensado (ADR)",IF(AND(LEFT(Q90,11)="Condicional",W90<>"",S90<>"",ISNUMBER(T90),T90>0,V90<>""),"DISPENSADO","REVISAR"),"PENDENTE"))
A91: 90 | B91: SL-S09-02 | C91: v0.1.0 | D91: S09 | E91: VaultGuard / ToolBroker | F91: Próprio | G91: Implementação | H91: Implementar resolução por IDs | I91: Converter referências em objetos autorizados dentro do Core. | J91: crates/security/src/object_broker.rs | K91: Texto vindo do modelo não pode se tornar path arbitrário por concatenação. | L91: SL-S09-01 | M91: R06; R08; R34 | N91: Não iniciado | O91: P0 | P91: Crítico | Q91: Obrigatória no escopo da versão | R91: Autor + agente de IA | U91: reports/S09/SL-S09-02.md | X91: =IF(N91="Concluído",IF(AND(S91<>"",ISNUMBER(T91),T91>0,V91<>"",AND(OR(X90="OK",X90="DISPENSADO"))),"OK","REVISAR"),IF(N91="Dispensado (ADR)",IF(AND(LEFT(Q91,11)="Condicional",W91<>"",S91<>"",ISNUMBER(T91),T91>0,V91<>""),"DISPENSADO","REVISAR"),"PENDENTE"))
A92: 91 | B92: SL-S09-03 | C92: v0.1.0 | D92: S09 | E92: VaultGuard / ToolBroker | F92: Próprio | G92: Implementação | H92: Implementar abertura Linux | I92: Usar diretório-base/handle e resolução restrita conforme kernel disponível. | J92: crates/security/src/fs/linux.rs | K92: Troca de symlink durante acesso não sai do escopo; recurso ausente tem política fail-closed. | L92: SL-S09-02 | M92: R06; R08; R34 | N92: Não iniciado | O92: P0 | P92: Crítico | Q92: Obrigatória no escopo da versão | R92: Autor + agente de IA | U92: reports/S09/SL-S09-03.md | X92: =IF(N92="Concluído",IF(AND(S92<>"",ISNUMBER(T92),T92>0,V92<>"",AND(OR(X91="OK",X91="DISPENSADO"))),"OK","REVISAR"),IF(N92="Dispensado (ADR)",IF(AND(LEFT(Q92,11)="Condicional",W92<>"",S92<>"",ISNUMBER(T92),T92>0,V92<>""),"DISPENSADO","REVISAR"),"PENDENTE"))
A93: 92 | B93: SL-S09-04 | C93: v0.1.0 | D93: S09 | E93: VaultGuard / ToolBroker | F93: Próprio | G93: Implementação | H93: Implementar abertura Windows | I93: Tratar handles, reparse points, junctions e canonicalização por mecanismo efetivo. | J93: crates/security/src/fs/windows.rs | K93: Junction trocada e path especial não contornam a autorização. | L93: SL-S09-03 | M93: R06; R08; R34 | N93: Não iniciado | O93: P0 | P93: Crítico | Q93: Obrigatória no escopo da versão | R93: Autor + agente de IA | U93: reports/S09/SL-S09-04.md | X93: =IF(N93="Concluído",IF(AND(S93<>"",ISNUMBER(T93),T93>0,V93<>"",AND(OR(X92="OK",X92="DISPENSADO"))),"OK","REVISAR"),IF(N93="Dispensado (ADR)",IF(AND(LEFT(Q93,11)="Condicional",W93<>"",S93<>"",ISNUMBER(T93),T93>0,V93<>""),"DISPENSADO","REVISAR"),"PENDENTE"))
A94: 93 | B94: SL-S09-05 | C94: v0.1.0 | D94: S09 | E94: VaultGuard / ToolBroker | F94: Próprio | G94: Implementação | H94: Implementar abertura macOS | I94: Usar primitivas relativas/handles e política de links consistente com o contrato. | J94: crates/security/src/fs/macos.rs | K94: Testes nativos demonstram contenção; não se reutiliza apenas canonicalize seguido de open. | L94: SL-S09-04 | M94: R06; R08; R34 | N94: Não iniciado | O94: P0 | P94: Crítico | Q94: Obrigatória no escopo da versão | R94: Autor + agente de IA | U94: reports/S09/SL-S09-05.md | X94: =IF(N94="Concluído",IF(AND(S94<>"",ISNUMBER(T94),T94>0,V94<>"",AND(OR(X93="OK",X93="DISPENSADO"))),"OK","REVISAR"),IF(N94="Dispensado (ADR)",IF(AND(LEFT(Q94,11)="Condicional",W94<>"",S94<>"",ISNUMBER(T94),T94>0,V94<>""),"DISPENSADO","REVISAR"),"PENDENTE"))
A95: 94 | B95: SL-S09-06 | C95: v0.1.0 | D95: S09 | E95: VaultGuard / ToolBroker | F95: Próprio | G95: Implementação | H95: Limitar leitura e escrita | I95: Aplicar tamanho, tipo e destino permitido; evitar arquivos especiais inesperados. | J95: crates/security/src/io_limits.rs | K95: Arquivo/dispositivo excessivo ou tipo indevido é rejeitado antes de consumo sem limite. | L95: SL-S09-05 | M95: R06; R08; R34 | N95: Não iniciado | O95: P0 | P95: Crítico | Q95: Obrigatória no escopo da versão | R95: Autor + agente de IA | U95: reports/S09/SL-S09-06.md | X95: =IF(N95="Concluído",IF(AND(S95<>"",ISNUMBER(T95),T95>0,V95<>"",AND(OR(X94="OK",X94="DISPENSADO"))),"OK","REVISAR"),IF(N95="Dispensado (ADR)",IF(AND(LEFT(Q95,11)="Condicional",W95<>"",S95<>"",ISNUMBER(T95),T95>0,V95<>""),"DISPENSADO","REVISAR"),"PENDENTE"))
A96: 95 | B96: SL-S09-07 | C96: v0.1.0 | D96: S09 | E96: VaultGuard / ToolBroker | F96: Próprio | G96: Implementação | H96: Autorizar fontes compartilhadas | I96: Separar assets/origens read-only de conteúdo privado de workspaces. | J96: crates/security/src/source_scope.rs | K96: Fonte aprovada pode ser lida sem conceder o diretório global inteiro. | L96: SL-S09-06 | M96: R06; R08; R34 | N96: Não iniciado | O96: P0 | P96: Crítico | Q96: Obrigatória no escopo da versão | R96: Autor + agente de IA | U96: reports/S09/SL-S09-07.md | X96: =IF(N96="Concluído",IF(AND(S96<>"",ISNUMBER(T96),T96>0,V96<>"",AND(OR(X95="OK",X95="DISPENSADO"))),"OK","REVISAR"),IF(N96="Dispensado (ADR)",IF(AND(LEFT(Q96,11)="Condicional",W96<>"",S96<>"",ISNUMBER(T96),T96>0,V96<>""),"DISPENSADO","REVISAR"),"PENDENTE"))
A97: 96 | B97: SL-S09-08 | C97: v0.1.0 | D97: S09 | E97: VaultGuard / ToolBroker | F97: Próprio | G97: Teste | H97: Criar corridas controladas | I97: Trocar symlinks/diretórios em loop de teste durante leituras. | J97: tests/security/toctou/ | K97: Harness registra nenhuma leitura de sentinela externa; falhas não são ignoradas. | L97: SL-S09-07 | M97: R06; R08; R34 | N97: Não iniciado | O97: P0 | P97: Crítico | Q97: Obrigatória no escopo da versão | R97: Autor + agente de IA | U97: reports/S09/SL-S09-08.md | X97: =IF(N97="Concluído",IF(AND(S97<>"",ISNUMBER(T97),T97>0,V97<>"",AND(OR(X96="OK",X96="DISPENSADO"))),"OK","REVISAR"),IF(N97="Dispensado (ADR)",IF(AND(LEFT(Q97,11)="Condicional",W97<>"",S97<>"",ISNUMBER(T97),T97>0,V97<>""),"DISPENSADO","REVISAR"),"PENDENTE"))
A98: 97 | B98: SL-S09-09 | C98: v0.1.0 | D98: S09 | E98: VaultGuard / ToolBroker | F98: Próprio | G98: Teste | H98: Cobrir nomes hostis e hard links | I98: Definir política explícita e testar absolutos, UNC, traversal e links. | J98: tests/security/path-policy/ | K98: Política é aplicada e limitações de hard links/mounts constam do relatório. | L98: SL-S09-08 | M98: R06; R08; R34 | N98: Não iniciado | O98: P0 | P98: Crítico | Q98: Obrigatória no escopo da versão | R98: Autor + agente de IA | U98: reports/S09/SL-S09-09.md | X98: =IF(N98="Concluído",IF(AND(S98<>"",ISNUMBER(T98),T98>0,V98<>"",AND(OR(X97="OK",X97="DISPENSADO"))),"OK","REVISAR"),IF(N98="Dispensado (ADR)",IF(AND(LEFT(Q98,11)="Condicional",W98<>"",S98<>"",ISNUMBER(T98),T98>0,V98<>""),"DISPENSADO","REVISAR"),"PENDENTE"))
A99: 98 | B99: SL-S09-10 | C99: v0.1.0 | D99: S09 | E99: VaultGuard / ToolBroker | F99: Próprio | G99: Teste | H99: Auditar APIs de filesystem | I99: Procurar acessos diretos fora dos módulos autorizados e criar regra de revisão. | J99: reports/security/fs-authority.md | K99: Fluxos de aplicação não têm bypass conhecido do broker para operações com dados não confiáveis. | L99: SL-S09-09 | M99: R06; R08; R34 | N99: Não iniciado | O99: P0 | P99: Crítico | Q99: Obrigatória no escopo da versão | R99: Autor + agente de IA | U99: reports/S09/SL-S09-10.md | X99: =IF(N99="Concluído",IF(AND(S99<>"",ISNUMBER(T99),T99>0,V99<>"",AND(OR(X98="OK",X98="DISPENSADO"))),"OK","REVISAR"),IF(N99="Dispensado (ADR)",IF(AND(LEFT(Q99,11)="Condicional",W99<>"",S99<>"",ISNUMBER(T99),T99>0,V99<>""),"DISPENSADO","REVISAR"),"PENDENTE"))
A100: 99 | B100: SL-S09-GATE | C100: v0.1.0 | D100: S09 | E100: VaultGuard / ToolBroker | F100: Aceite humano | G100: Gate | H100: Aceitar S09 — Implementar broker de arquivos e defesa TOCTOU | I100: Revisar as dez tarefas, executar a demonstração do sprint, confrontar critérios e registrar decisão go/no-go. | J100: reports/S09/acceptance.md | K100: Solicitar um arquivo permitido e negar escapes durante resolução e concorrência. Todas as dependências aceitas; evidências vinculadas a revisão/ambiente; nenhum blocker de integridade/segurança. | L100: SL-S09-01; SL-S09-02; SL-S09-03; SL-S09-04; SL-S09-05; SL-S09-06; SL-S09-07; SL-S09-08; SL-S09-09; SL-S09-10 | M100: R06; R08; R34 | N100: Não iniciado | O100: P0 | P100: Crítico | Q100: Obrigatória para fechar a versão aprovada | R100: Autor | U100: reports/S09/acceptance.md | X100: =IF(N100="Concluído",IF(AND(S100<>"",ISNUMBER(T100),T100>0,V100<>"",AND(OR(X90="OK",X90="DISPENSADO"),OR(X91="OK",X91="DISPENSADO"),OR(X92="OK",X92="DISPENSADO"),OR(X93="OK",X93="DISPENSADO"),OR(X94="OK",X94="DISPENSADO"),OR(X95="OK",X95="DISPENSADO"),OR(X96="OK",X96="DISPENSADO"),OR(X97="OK",X97="DISPENSADO"),OR(X98="OK",X98="DISPENSADO"),OR(X99="OK",X99="DISPENSADO"))),"OK","REVISAR"),IF(N100="Dispensado (ADR)",IF(AND(LEFT(Q100,11)="Condicional",W100<>"",S100<>"",ISNUMBER(T100),T100>0,V100<>""),"DISPENSADO","REVISAR"),"PENDENTE"))
...

Sheet Versões
A1: Versão | B1: Nome | C1: Maturidade | D1: Sprints | E1: Nº sprints | F1: Tarefas | G1: Gates | H1: Entregável diferente | I1: Tarefas aceitas | J1: Gates aceitos | K1: Tarefas dispensadas | L1: Progresso aplicável
A2: v0.0.1 | B2: Arquitetura executável | C2: Interna | D2: S01–S03 | E2: 3 | F2: 30 | G2: 3 | H2: Decisões, contratos de dados e inventário de origem aprovados; nenhuma funcionalidade de produto prometida. | I2: =COUNTIFS(Tarefas!$C$2:$C$793,A2,Tarefas!$G$2:$G$793,"<>Gate",Tarefas!$X$2:$X$793,"OK") | J2: =COUNTIFS(Tarefas!$C$2:$C$793,A2,Tarefas!$G$2:$G$793,"Gate",Tarefas!$X$2:$X$793,"OK") | K2: =COUNTIFS(Tarefas!$C$2:$C$793,A2,Tarefas!$G$2:$G$793,"<>Gate",Tarefas!$X$2:$X$793,"DISPENSADO") | L2: =IFERROR(I2/(F2-K2),0)
A3: v0.0.2 | B3: Bancada reproduzível | C3: Interna | D3: S04–S06 | E3: 3 | F3: 30 | G3: 3 | H3: Repositório, CI, fixtures e shell desktop compiláveis sem importar aplicações completas. | I3: =COUNTIFS(Tarefas!$C$2:$C$793,A3,Tarefas!$G$2:$G$793,"<>Gate",Tarefas!$X$2:$X$793,"OK") | J3: =COUNTIFS(Tarefas!$C$2:$C$793,A3,Tarefas!$G$2:$G$793,"Gate",Tarefas!$X$2:$X$793,"OK") | K3: =COUNTIFS(Tarefas!$C$2:$C$793,A3,Tarefas!$G$2:$G$793,"<>Gate",Tarefas!$X$2:$X$793,"DISPENSADO") | L3: =IFERROR(I3/(F3-K3),0)
A4: v0.1.0 | B4: Vault recuperável | C4: Alpha técnica | D4: S07–S11 | E4: 5 | F4: 50 | G4: 5 | H4: Criar, alterar, recuperar e reconstruir conhecimento local com ferramenta de diagnóstico. | I4: =COUNTIFS(Tarefas!$C$2:$C$793,A4,Tarefas!$G$2:$G$793,"<>Gate",Tarefas!$X$2:$X$793,"OK") | J4: =COUNTIFS(Tarefas!$C$2:$C$793,A4,Tarefas!$G$2:$G$793,"Gate",Tarefas!$X$2:$X$793,"OK") | K4: =COUNTIFS(Tarefas!$C$2:$C$793,A4,Tarefas!$G$2:$G$793,"<>Gate",Tarefas!$X$2:$X$793,"DISPENSADO") | L4: =IFERROR(I4/(F4-K4),0)
A5: v0.2.0 | B5: Editor local BlockSuite | C5: Alpha de autoria | D5: S12–S15 | E5: 4 | F5: 40 | G5: 4 | H5: Editar notas no perfil Markdown suportado e reabrir sem depender do estado interno do editor. | I5: =COUNTIFS(Tarefas!$C$2:$C$793,A5,Tarefas!$G$2:$G$793,"<>Gate",Tarefas!$X$2:$X$793,"OK") | J5: =COUNTIFS(Tarefas!$C$2:$C$793,A5,Tarefas!$G$2:$G$793,"Gate",Tarefas!$X$2:$X$793,"OK") | K5: =COUNTIFS(Tarefas!$C$2:$C$793,A5,Tarefas!$G$2:$G$793,"<>Gate",Tarefas!$X$2:$X$793,"DISPENSADO") | L5: =IFERROR(I5/(F5-K5),0)
A6: v0.3.0 | B6: Mesa espacial | C6: Alpha de autoria | D6: S16–S19 | E6: 4 | F6: 40 | G6: 4 | H6: Organizar células, grupos e relações com PixiJS e edição BlockSuite integrada. | I6: =COUNTIFS(Tarefas!$C$2:$C$793,A6,Tarefas!$G$2:$G$793,"<>Gate",Tarefas!$X$2:$X$793,"OK") | J6: =COUNTIFS(Tarefas!$C$2:$C$793,A6,Tarefas!$G$2:$G$793,"Gate",Tarefas!$X$2:$X$793,"OK") | K6: =COUNTIFS(Tarefas!$C$2:$C$793,A6,Tarefas!$G$2:$G$793,"<>Gate",Tarefas!$X$2:$X$793,"DISPENSADO") | L6: =IFERROR(I6/(F6-K6),0)
A7: v0.4.0 | B7: Peça e proveniência | C7: Alpha funcional sem IA | D7: S20–S22 | E7: 3 | F7: 30 | G7: 3 | H7: Produzir texto editorial a partir da Mesa com fork-on-insert, referências e exportação. | I7: =COUNTIFS(Tarefas!$C$2:$C$793,A7,Tarefas!$G$2:$G$793,"<>Gate",Tarefas!$X$2:$X$793,"OK") | J7: =COUNTIFS(Tarefas!$C$2:$C$793,A7,Tarefas!$G$2:$G$793,"Gate",Tarefas!$X$2:$X$793,"OK") | K7: =COUNTIFS(Tarefas!$C$2:$C$793,A7,Tarefas!$G$2:$G$793,"<>Gate",Tarefas!$X$2:$X$793,"DISPENSADO") | L7: =IFERROR(I7/(F7-K7),0)
A8: v0.5.0 | B8: Ingestão segura | C8: Alpha de acervo | D8: S23–S30 | E8: 8 | F8: 80 | G8: 8 | H8: Capturar arquivos/HTML, extrair texto e OCR em workers confinados e organizar o acervo. | I8: =COUNTIFS(Tarefas!$C$2:$C$793,A8,Tarefas!$G$2:$G$793,"<>Gate",Tarefas!$X$2:$X$793,"OK") | J8: =COUNTIFS(Tarefas!$C$2:$C$793,A8,Tarefas!$G$2:$G$793,"Gate",Tarefas!$X$2:$X$793,"OK") | K8: =COUNTIFS(Tarefas!$C$2:$C$793,A8,Tarefas!$G$2:$G$793,"<>Gate",Tarefas!$X$2:$X$793,"DISPENSADO") | L8: =IFERROR(I8/(F8-K8),0)
A9: v0.6.0 | B9: Enriquecimento e modelos | C9: Alpha assistida | D9: S31–S36 | E9: 6 | F9: 60 | G9: 6 | H9: LocalAI gerenciado, resumos, Jev autorizado, fallback local e transcrição homologada. | I9: =COUNTIFS(Tarefas!$C$2:$C$793,A9,Tarefas!$G$2:$G$793,"<>Gate",Tarefas!$X$2:$X$793,"OK") | J9: =COUNTIFS(Tarefas!$C$2:$C$793,A9,Tarefas!$G$2:$G$793,"Gate",Tarefas!$X$2:$X$793,"OK") | K9: =COUNTIFS(Tarefas!$C$2:$C$793,A9,Tarefas!$G$2:$G$793,"<>Gate",Tarefas!$X$2:$X$793,"DISPENSADO") | L9: =IFERROR(I9/(F9-K9),0)
A10: v0.7.0 | B10: Busca híbrida | C10: Alpha integrada | D10: S37–S41 | E10: 5 | F10: 50 | G10: 5 | H10: Escolher Qdrant OU HelixDB e recuperar materiais/Peças com índices descartáveis e revisões válidas. | I10: =COUNTIFS(Tarefas!$C$2:$C$793,A10,Tarefas!$G$2:$G$793,"<>Gate",Tarefas!$X$2:$X$793,"OK") | J10: =COUNTIFS(Tarefas!$C$2:$C$793,A10,Tarefas!$G$2:$G$793,"Gate",Tarefas!$X$2:$X$793,"OK") | K10: =COUNTIFS(Tarefas!$C$2:$C$793,A10,Tarefas!$G$2:$G$793,"<>Gate",Tarefas!$X$2:$X$793,"DISPENSADO") | L10: =IFERROR(I10/(F10-K10),0)
A11: v0.8.0 | B11: Contexto estrutural | C11: Alpha de raciocínio | D11: S42–S46 | E11: 5 | F11: 50 | G11: 5 | H11: PageIndex adaptado às células, Skeleton Map e recuperação relacional limitada por escopo e orçamento. | I11: =COUNTIFS(Tarefas!$C$2:$C$793,A11,Tarefas!$G$2:$G$793,"<>Gate",Tarefas!$X$2:$X$793,"OK") | J11: =COUNTIFS(Tarefas!$C$2:$C$793,A11,Tarefas!$G$2:$G$793,"Gate",Tarefas!$X$2:$X$793,"OK") | K11: =COUNTIFS(Tarefas!$C$2:$C$793,A11,Tarefas!$G$2:$G$793,"<>Gate",Tarefas!$X$2:$X$793,"DISPENSADO") | L11: =IFERROR(I11/(F11-K11),0)
A12: v0.9.0 | B12: Ciclo analítico completo | C12: Alpha de ciclo completo | D12: S47–S53 | E12: 7 | F12: 70 | G12: 7 | H12: Pesquisa web, widget, copiloto, chat e intenções conectam Captura → Mesa → Peça. | I12: =COUNTIFS(Tarefas!$C$2:$C$793,A12,Tarefas!$G$2:$G$793,"<>Gate",Tarefas!$X$2:$X$793,"OK") | J12: =COUNTIFS(Tarefas!$C$2:$C$793,A12,Tarefas!$G$2:$G$793,"Gate",Tarefas!$X$2:$X$793,"OK") | K12: =COUNTIFS(Tarefas!$C$2:$C$793,A12,Tarefas!$G$2:$G$793,"<>Gate",Tarefas!$X$2:$X$793,"DISPENSADO") | L12: =IFERROR(I12/(F12-K12),0)
A13: v1.0.0-beta.1 | B13: Homologação multiplataforma | C13: Beta | D13: S54–S57 | E13: 4 | F13: 40 | G13: 4 | H13: Segurança, performance e pacotes validados nos cinco alvos, sem presumir paridade de aceleração. | I13: =COUNTIFS(Tarefas!$C$2:$C$793,A13,Tarefas!$G$2:$G$793,"<>Gate",Tarefas!$X$2:$X$793,"OK") | J13: =COUNTIFS(Tarefas!$C$2:$C$793,A13,Tarefas!$G$2:$G$793,"Gate",Tarefas!$X$2:$X$793,"OK") | K13: =COUNTIFS(Tarefas!$C$2:$C$793,A13,Tarefas!$G$2:$G$793,"<>Gate",Tarefas!$X$2:$X$793,"DISPENSADO") | L13: =IFERROR(I13/(F13-K13),0)
... A20: v2.0.0 | B20: Plataforma estável e sustentável | C20: Estável — fim do horizonte | D20: S72–S72 | E20: 1 | F20: 10 | G20: 1 | H20: Base madura, interoperável e extensível; continuidade de manutenção, não fim definitivo do projeto. | I20: =COUNTIFS(Tarefas!$C$2:$C$793,A20,Tarefas!$G$2:$G$793,"<>Gate",Tarefas!$X$2:$X$793,"OK") | J20: =COUNTIFS(Tarefas!$C$2:$C$793,A20,Tarefas!$G$2:$G$793,"Gate",Tarefas!$X$2:$X$793,"OK") | K20: =COUNTIFS(Tarefas!$C$2:$C$793,A20,Tarefas!$G$2:$G$793,"<>Gate",Tarefas!$X$2:$X$793,"DISPENSADO") | L20: =IFERROR(I20/(F20-K20),0)

Sheet Sprints
A1: Sprint | B1: Versão | C1: Objetivo curto | D1: Objetivo verificável | E1: Componente | F1: Forma | G1: Pré-requisitos técnicos | H1: Requisitos | I1: Entrega | J1: Demonstração de aceite | K1: Gate | L1: Risco | M1: Observação | N1: Tarefas aceitas | O1: Total tarefas | P1: Dispensadas válidas | Q1: Progresso aplicável
A2: S01 | B2: v0.0.1 | C2: Ratificar escopo, soberania e composição | D2: Eliminar decisões contraditórias antes de criar dependências de implementação. | E2: Arquitetura / produto | F2: Próprio | H2: R01; R03; R07; R08; R33; R34 | I2: Escopo v1.0 e registro de decisões iniciais. | J2: Autor consegue explicar offline, Jev, workers e cinco alvos sem contradições. | K2: SL-S01-GATE | L2: Crítico | N2: =COUNTIFS(Tarefas!$D$2:$D$793,A2,Tarefas!$G$2:$G$793,"<>Gate",Tarefas!$X$2:$X$793,"OK") | O2: 10 | P2: =COUNTIFS(Tarefas!$D$2:$D$793,A2,Tarefas!$G$2:$G$793,"<>Gate",Tarefas!$X$2:$X$793,"DISPENSADO") | Q2: =IFERROR(N2/(O2-P2),0)
A3: S02 | B3: v0.0.1 | C3: Definir formatos, identidade e autoridade | D3: Especificar representação persistente antes do editor e dos índices. | E3: Vault / contratos | F3: Próprio | G3: S01 | H3: R02; R04; R05; R11; R13; R32; R37 | I3: Schemas v0 do Vault, board, eventos, células e evidências. | J3: Fixtures independentes dos motores representam uma mesa e uma Peça completas. | K3: SL-S02-GATE | L3: Crítico | N3: =COUNTIFS(Tarefas!$D$2:$D$793,A3,Tarefas!$G$2:$G$793,"<>Gate",Tarefas!$X$2:$X$793,"OK") | O3: 10 | P3: =COUNTIFS(Tarefas!$D$2:$D$793,A3,Tarefas!$G$2:$G$793,"<>Gate",Tarefas!$X$2:$X$793,"DISPENSADO") | Q3: =IFERROR(N3/(O3-P3),0)
A4: S03 | B4: v0.0.1 | C4: Inventariar upstreams e definir recortes | D4: Fixar origem, licenças e modo de integração sem criar forks indiscriminados. | E4: Todos os motores / licenças | F4: Desconstrução | G4: S01; S02 | H4: R03; R30; R33; R34 | I4: Catálogo de componentes e política de manutenção upstream. | J4: Cada motor tem origem rastreável, fronteira proposta e decisão de manter/extrair/adaptar. | K4: SL-S03-GATE | L4: Crítico | N4: =COUNTIFS(Tarefas!$D$2:$D$793,A4,Tarefas!$G$2:$G$793,"<>Gate",Tarefas!$X$2:$X$793,"OK") | O4: 10 | P4: =COUNTIFS(Tarefas!$D$2:$D$793,A4,Tarefas!$G$2:$G$793,"<>Gate",Tarefas!$X$2:$X$793,"DISPENSADO") | Q4: =IFERROR(N4/(O4-P4),0)
A5: S04 | B5: v0.0.2 | C5: Montar repositório e fluxo solo com IA | D5: Tornar alterações pequenas, revisáveis e reproduzíveis por um único mantenedor. | E5: Ferramentas / governança | F5: Próprio | G5: S03 | H5: R03; R30; R33; R34 | I5: Monorepo de trabalho e instruções de contribuição/agentes. | J5: Um agente implementa uma tarefa isolada e o autor consegue revisar o patch e seus testes. | K5: SL-S04-GATE | L5: Crítico | N5: =COUNTIFS(Tarefas!$D$2:$D$793,A5,Tarefas!$G$2:$G$793,"<>Gate",Tarefas!$X$2:$X$793,"OK") | O5: 10 | P5: =COUNTIFS(Tarefas!$D$2:$D$793,A5,Tarefas!$G$2:$G$793,"<>Gate",Tarefas!$X$2:$X$793,"DISPENSADO") | Q5: =IFERROR(N5/(O5-P5),0)
A6: S05 | B6: v0.0.2 | C6: Construir CI, corpus e protocolo de medição | D6: Criar a bancada que impedirá promessas de qualidade ou recursos sem medição. | E6: Qualidade / desempenho | F6: Próprio | G6: S04 | H6: R01; R09; R12; R15; R20; R34 | I6: CI inicial, corpus licenciado e perfis mensuráveis. | J6: Falha introduzida em contrato bloqueia pipeline e um benchmark gera dados reproduzíveis. | K6: SL-S05-GATE | L6: Alto | N6: =COUNTIFS(Tarefas!$D$2:$D$793,A6,Tarefas!$G$2:$G$793,"<>Gate",Tarefas!$X$2:$X$793,"OK") | O6: 10 | P6: =COUNTIFS(Tarefas!$D$2:$D$793,A6,Tarefas!$G$2:$G$793,"<>Gate",Tarefas!$X$2:$X$793,"DISPENSADO") | Q6: =IFERROR(N6/(O6-P6),0)
A7: S06 | B7: v0.0.2 | C7: Criar shell desktop e contratos IPC | D7: Abrir um app local mínimo sem antecipar a integração de todos os motores. | E7: Tauri / apresentação | F7: Integração | G7: S04; S05 | H7: R01; R03; R07; R08; R31; R34 | I7: Shell Tauri com navegação Ingest/Mesa/Peça e IPC validado. | J7: Instalar build de desenvolvimento, navegar e selecionar um diretório sem rede. | K7: SL-S06-GATE | L7: Crítico | N7: =COUNTIFS(Tarefas!$D$2:$D$793,A7,Tarefas!$G$2:$G$793,"<>Gate",Tarefas!$X$2:$X$793,"OK") | O7: 10 | P7: =COUNTIFS(Tarefas!$D$2:$D$793,A7,Tarefas!$G$2:$G$793,"<>Gate",Tarefas!$X$2:$X$793,"DISPENSADO") | Q7: =IFERROR(N7/(O7-P7),0)
A8: S07 | B8: v0.1.0 | C8: Implementar Vault, identidade e assets | D8: Criar a primeira autoridade persistente do produto. | E8: VaultStore / CAS | F8: Próprio | G8: S02; S06 | H8: R02; R04; R05; R07 | I8: VaultStore básico, manifest e armazenamento de assets por hash. | J8: Criar Vault, salvar nota/asset, fechar e listar os mesmos IDs ao reabrir. | K8: SL-S07-GATE | L8: Crítico | N8: =COUNTIFS(Tarefas!$D$2:$D$793,A8,Tarefas!$G$2:$G$793,"<>Gate",Tarefas!$X$2:$X$793,"OK") | O8: 10 | P8: =COUNTIFS(Tarefas!$D$2:$D$793,A8,Tarefas!$G$2:$G$793,"<>Gate",Tarefas!$X$2:$X$793,"DISPENSADO") | Q8: =IFERROR(N8/(O8-P8),0)
A9: S08 | B9: v0.1.0 | C9: Implementar transações de arquivos e histórico | D9: Tornar confirmação, replay e desfazer independentes de bancos descartáveis. | E9: Journal / RevisionStore | F9: Próprio | G9: S07 | H9: R02; R05; R13; R37 | I9: Journal durável e protocolo de publicação de revisões. | J9: Interromper cada etapa de uma edição e recuperar o último estado confirmado. | K9: SL-S08-GATE | L9: Crítico | N9: =COUNTIFS(Tarefas!$D$2:$D$793,A9,Tarefas!$G$2:$G$793,"<>Gate",Tarefas!$X$2:$X$793,"OK") | O9: 10 | P9: =COUNTIFS(Tarefas!$D$2:$D$793,A9,Tarefas!$G$2:$G$793,"<>Gate",Tarefas!$X$2:$X$793,"DISPENSADO") | Q9: =IFERROR(N9/(O9-P9),0)
A10: S09 | B10: v0.1.0 | C10: Implementar broker de arquivos e defesa TOCTOU | D10: Eliminar validação de path separada da abertura antes de integrar workers. | E10: VaultGuard / ToolBroker | F10: Próprio | G10: S07; S08 | H10: R06; R08; R34 | I10: I/O autorizado por referências/handles e suíte de ataques de paths. | J10: Solicitar um arquivo permitido e negar escapes durante resolução e concorrência. | K10: SL-S09-GATE | L10: Crítico | N10: =COUNTIFS(Tarefas!$D$2:$D$793,A10,Tarefas!$G$2:$G$793,"<>Gate",Tarefas!$X$2:$X$793,"OK") | O10: 10 | P10: =COUNTIFS(Tarefas!$D$2:$D$793,A10,Tarefas!$G$2:$G$793,"<>Gate",Tarefas!$X$2:$X$793,"DISPENSADO") | Q10: =IFERROR(N10/(O10-P10),0)
A11: S10 | B11: v0.1.0 | C11: Reconciliar alterações externas e reconstruir índices | D11: Manter o disco como autoridade mesmo com edição externa e perda de notificações. | E11: Watcher / projeções | F11: Próprio | G11: S08; S09 | H11: R02; R04; R05; R21 | I11: Reconciliação incremental e cache de inventário descartável. | J11: Editar/renomear fora do app, perder um evento de watcher e reconciliar sem perda. | K11: SL-S10-GATE | L11: Crítico | N11: =COUNTIFS(Tarefas!$D$2:$D$793,A11,Tarefas!$G$2:$G$793,"<>Gate",Tarefas!$X$2:$X$793,"OK") | O11: 10 | P11: =COUNTIFS(Tarefas!$D$2:$D$793,A11,Tarefas!$G$2:$G$793,"<>Gate",Tarefas!$X$2:$X$793,"DISPENSADO") | Q11: =IFERROR(N11/(O11-P11),0)
A12: S11 | B12: v0.1.0 | C12: Concluir v0.1: recuperação e diagnóstico do Vault | D12: Entregar um núcleo de dados utilizável antes de adicionar complexidade visual. | E12: Vault / integração | F12: Próprio | G12: S07; S08; S09; S10 | H12: R02; R05; R06; R07; R29; R34 | I12: v0.1.0 alpha técnica e utilitário de recuperação. | J12: Criar, modificar, corromper um cache, reconstruir e exportar um Vault local. | K12: SL-S11-GATE | L12: Crítico | N12: =COUNTIFS(Tarefas!$D$2:$D$793,A12,Tarefas!$G$2:$G$793,"<>Gate",Tarefas!$X$2:$X$793,"OK") | O12: 10 | P12: =COUNTIFS(Tarefas!$D$2:$D$793,A12,Tarefas!$G$2:$G$793,"<>Gate",Tarefas!$X$2:$X$793,"DISPENSADO") | Q12: =IFERROR(N12/(O12-P12),0)
A13: S12 | B13: v0.2.0 | C13: Extrair o recorte editorial do BlockSuite | D13: Reproduzir a edição mínima sem importar o produto AFFiNE. | E13: BlockSuite / upstream | F13: Desconstrução | G13: S03; S04; S06; S11 | H13: R03; R10; R30; R33; R34 | I13: Pacote editorial isolado e ADR do recorte. | J13: Editor mínimo funciona fora do monorepo de origem e sua origem/licença é rastreável. | K13: SL-S12-GATE | L13: Crítico | N13: =COUNTIFS(Tarefas!$D$2:$D$793,A13,Tarefas!$G$2:$G$793,"<>Gate",Tarefas!$X$2:$X$793,"OK") | O13: 10 | P13: =COUNTIFS(Tarefas!$D$2:$D$793,A13,Tarefas!$G$2:$G$793,"<>Gate",Tarefas!$X$2:$X$793,"DISPENSADO") | Q13: =IFERROR(N13/(O13-P13),0)
A14: S13 | B14: v0.2.0 | C14: Implementar ponte Markdown ↔ BlockSuite | D14: Conectar o modelo editorial ao formato autoral sem perda silenciosa. | E14: EditorBridge / formato | F14: Adaptação | G14: S02; S12 | H14: R02; R04; R10; R13; R32 | I14: Serializer/deserializer e fixtures de round-trip. | J14: Abrir Markdown externo, editar no BlockSuite e preservar a semântica e metadados. | K14: SL-S13-GATE | L14: Alto | N14: =COUNTIFS(Tarefas!$D$2:$D$793,A14,Tarefas!$G$2:$G$793,"<>Gate",Tarefas!$X$2:$X$793,"OK") | O14: 10 | P14: =COUNTIFS(Tarefas!$D$2:$D$793,A14,Tarefas!$G$2:$G$793,"<>Gate",Tarefas!$X$2:$X$793,"DISPENSADO") | Q14: =IFERROR(N14/(O14-P14),0)
... A38: S37 | B38: v0.7.0 | C38: Definir contrato e bancada de busca híbrida | D38: Comparar motores sob o mesmo contrato antes de escolhê-los. | E38: SearchService / avaliação | F38: Próprio | G38: S05; S10; S22; S32; S36 | H38: R02; R20; R21; R34 | I38: Contrato de busca, indexação e protocolo comparativo. | J38: Mesma fixture/consulta roda em providers fake e produz ranking/evidências verificáveis. | K38: SL-S37-GATE | L38: Médio | N38: =COUNTIFS(Tarefas!$D$2:$D$793,A38,Tarefas!$G$2:$G$793,"<>Gate",Tarefas!$X$2:$X$793,"OK") | O38: 10 | P38: =COUNTIFS(Tarefas!$D$2:$D$793,A38,Tarefas!$G$2:$G$793,"<>Gate",Tarefas!$X$2:$X$793,"DISPENSADO") | Q38: =IFERROR(N38/(O38-P38),0)
A39: S38 | B39: v0.7.0 | C39: Avaliar Qdrant sem incorporar servidor completo | D39: Testar Edge/Server adequados ao desktop com recorte experimental descartável. | E39: Qdrant / candidato A | F39: Spike de motor | G39: S37 | H39: R01; R20; R21; R30; R33 | I39: Relatório Qdrant e provider experimental. | J39: Executar conformidade e benchmarks iguais ao candidato B, com conclusão viável/inviável. | K39: SL-S38-GATE | L39: Crítico | M39: Este sprint fecha uma investigação, não aprova automaticamente Qdrant para produção. Conclusão negativa fundamentada é uma saída válida do spike. | N39: =COUNTIFS(Tarefas!$D$2:$D$793,A39,Tarefas!$G$2:$G$793,"<>Gate",Tarefas!$X$2:$X$793,"OK") | O39: 10 | P39: =COUNTIFS(Tarefas!$D$2:$D$793,A39,Tarefas!$G$2:$G$793,"<>Gate",Tarefas!$X$2:$X$793,"DISPENSADO") | Q39: =IFERROR(N39/(O39-P39),0)
A40: S39 | B40: v0.7.0 | C40: Avaliar HelixDB sob o mesmo contrato | D40: Medir integração embutida e busca/grafo sem tornar HelixDB fonte da verdade. | E40: HelixDB / candidato B | F40: Spike de motor | G40: S37 | H40: R01; R20; R21; R30; R33 | I40: Relatório HelixDB e provider experimental. | J40: Rodar o mesmo corpus e confrontar resultados com o candidato A. | K40: SL-S39-GATE | L40: Crítico | M40: Concluir o spike não implica adotar HelixDB. Os dois protótipos ficam em experiments e não são distribuídos juntos por padrão. | N40: =COUNTIFS(Tarefas!$D$2:$D$793,A40,Tarefas!$G$2:$G$793,"<>Gate",Tarefas!$X$2:$X$793,"OK") | O40: 10 | P40: =COUNTIFS(Tarefas!$D$2:$D$793,A40,Tarefas!$G$2:$G$793,"<>Gate",Tarefas!$X$2:$X$793,"DISPENSADO") | Q40: =IFERROR(N40/(O40-P40),0)
A41: S40 | B41: v0.7.0 | C41: Escolher e integrar um backend de busca | D41: Converter evidência comparativa em uma implementação de produto, não em dual-stack. | E41: Qdrant OU HelixDB / produção | F41: Integração | G41: S38; S39 | H41: R02; R20; R21; R30; R32 | I41: SearchProvider de produção e ADR de seleção. | J41: Executar busca híbrida no app com apenas o backend escolhido instalado. | K41: SL-S40-GATE | L41: Crítico | N41: =COUNTIFS(Tarefas!$D$2:$D$793,A41,Tarefas!$G$2:$G$793,"<>Gate",Tarefas!$X$2:$X$793,"OK") | O41: 10 | P41: =COUNTIFS(Tarefas!$D$2:$D$793,A41,Tarefas!$G$2:$G$793,"<>Gate",Tarefas!$X$2:$X$793,"DISPENSADO") | Q41: =IFERROR(N41/(O41-P41),0)
A42: S41 | B42: v0.7.0 | C42: Entregar busca incremental no acervo e nas Peças | D42: Fazer recuperação refletir revisões, exclusões e diferentes tipos de autoria. | E42: SearchService / UI | F42: Integração | G42: S35; S40 | H42: R02; R05; R13; R20; R21; R31 | I42: v0.7.0 com busca híbrida e reconstrução assistida. | J42: Editar/excluir material e verificar atualização da busca sem perder as fontes canônicas. | K42: SL-S41-GATE | L42: Crítico | N42: =COUNTIFS(Tarefas!$D$2:$D$793,A42,Tarefas!$G$2:$G$793,"<>Gate",Tarefas!$X$2:$X$793,"OK") | O42: 10 | P42: =COUNTIFS(Tarefas!$D$2:$D$793,A42,Tarefas!$G$2:$G$793,"<>Gate",Tarefas!$X$2:$X$793,"DISPENSADO") | Q42: =IFERROR(N42/(O42-P42),0)
A43: S42 | B43: v0.8.0 | C43: Auditar e recortar PageIndex para células | D43: Identificar código reaproveitável e pontos que precisam perder acoplamento documental/cloud. | E43: PageIndex / upstream | F43: Desconstrução | G43: S03; S23; S32; S41 | H43: R03; R22; R23; R30; R33 | I43: Pacote experimental de contexto e ADR do recorte PageIndex. | J43: Construir índice de Markdown de fixture sem PDF e sem store canônico do SDK. | K43: SL-S42-GATE | L43: Crítico | N43: =COUNTIFS(Tarefas!$D$2:$D$793,A43,Tarefas!$G$2:$G$793,"<>Gate",Tarefas!$X$2:$X$793,"OK") | O43: 10 | P43: =COUNTIFS(Tarefas!$D$2:$D$793,A43,Tarefas!$G$2:$G$793,"<>Gate",Tarefas!$X$2:$X$793,"DISPENSADO") | Q43: =IFERROR(N43/(O43-P43),0)
A44: S43 | B44: v0.8.0 | C44: Projetar a topologia em índice estrutural estável | D44: Transformar workspace/células em hierarquia navegável sem perder o grafo. | E44: PageIndex / StructureAdapter | F44: Adaptação | G44: S17; S42 | H44: R02; R04; R11; R22; R32 | I44: WorkspaceSnapshot e índice estrutural por revisão. | J44: Renomear notas, mover cartões e reconstruir mantendo IDs e referências. | K44: SL-S43-GATE | L44: Alto | N44: =COUNTIFS(Tarefas!$D$2:$D$793,A44,Tarefas!$G$2:$G$793,"<>Gate",Tarefas!$X$2:$X$793,"OK") | O44: 10 | P44: =COUNTIFS(Tarefas!$D$2:$D$793,A44,Tarefas!$G$2:$G$793,"<>Gate",Tarefas!$X$2:$X$793,"DISPENSADO") | Q44: =IFERROR(N44/(O44-P44),0)
A45: S44 | B45: v0.8.0 | C45: Criar ferramentas de contexto com escopo efetivo | D45: Permitir exploração pelo modelo sem lhe entregar o Vault ou a biblioteca global. | E45: ToolBroker / PageIndex | F45: Adaptação | G45: S09; S26; S43 | H45: R06; R08; R22; R23 | I45: Ferramentas de overview, grupo, célula, vizinhos e fonte. | J45: Modelo recebe ID fora do escopo e o broker nega mesmo com instrução em documento. | K45: SL-S44-GATE | L45: Crítico | N45: =COUNTIFS(Tarefas!$D$2:$D$793,A45,Tarefas!$G$2:$G$793,"<>Gate",Tarefas!$X$2:$X$793,"OK") | O45: 10 | P45: =COUNTIFS(Tarefas!$D$2:$D$793,A45,Tarefas!$G$2:$G$793,"<>Gate",Tarefas!$X$2:$X$793,"DISPENSADO") | Q45: =IFERROR(N45/(O45-P45),0)
A46: S45 | B46: v0.8.0 | C46: Implementar summaries incrementais e Skeleton Map | D46: Usar síntese estrutural dentro do contexto dos modelos locais e com invalidação precisa. | E46: ContextService / LocalAI | F46: Próprio | G46: S33; S43; S44 | H46: R09; R19; R22; R23 | I46: Skeleton Map com budget e cache incremental de resumos. | J46: Editar uma célula e recomputar apenas summaries dependentes, sem perder evidências. | K46: SL-S45-GATE | L46: Alto | N46: =COUNTIFS(Tarefas!$D$2:$D$793,A46,Tarefas!$G$2:$G$793,"<>Gate",Tarefas!$X$2:$X$793,"OK") | O46: 10 | P46: =COUNTIFS(Tarefas!$D$2:$D$793,A46,Tarefas!$G$2:$G$793,"<>Gate",Tarefas!$X$2:$X$793,"DISPENSADO") | Q46: =IFERROR(N46/(O46-P46),0)
A47: S46 | B47: v0.8.0 | C47: Entregar recuperação estrutural e síntese progressiva | D47: Fechar o motor da Mesa com evidências, abstenção e limites de execução. | E47: Context Engine / orquestração | F47: Integração | G47: S44; S45 | H47: R07; R13; R22; R23; R27 | I47: v0.8.0: consulta estrutural local sobre células e fontes. | J47: Perguntar sobre grupos que se contradizem e receber resposta apoiada nas revisões corretas. | K47: SL-S46-GATE | L47: Alto | N47: =COUNTIFS(Tarefas!$D$2:$D$793,A47,Tarefas!$G$2:$G$793,"<>Gate",Tarefas!$X$2:$X$793,"OK") | O47: 10 | P47: =COUNTIFS(Tarefas!$D$2:$D$793,A47,Tarefas!$G$2:$G$793,"<>Gate",Tarefas!$X$2:$X$793,"DISPENSADO") | Q47: =IFERROR(N47/(O47-P47),0)
A48: S47 | B48: v0.9.0 | C48: Integrar SearxNG como serviço de descoberta | D48: Usar metabusca sem incorporar sua UI ou criar dependência pública implícita. | E48: SearxNG / WebDiscoveryProvider | F48: Desconstrução | G48: S23; S26; S34; S46 | H48: R08; R24; R30; R33 | I48: Provider SearxNG com configuração, consentimento e testes de resposta. | J48: Pesquisar por consulta autorizada e apresentar resultados sem enviar o board inteiro. | K48: SL-S47-GATE | L48: Crítico | N48: =COUNTIFS(Tarefas!$D$2:$D$793,A48,Tarefas!$G$2:$G$793,"<>Gate",Tarefas!$X$2:$X$793,"OK") | O48: 10 | P48: =COUNTIFS(Tarefas!$D$2:$D$793,A48,Tarefas!$G$2:$G$793,"<>Gate",Tarefas!$X$2:$X$793,"DISPENSADO") | Q48: =IFERROR(N48/(O48-P48),0)
A49: S48 | B49: v0.9.0 | C49: Integrar Scrapling no caminho HTTP | D49: Adquirir páginas com limites e origem preservada antes de habilitar um browser. | E49: Scrapling / WebFetchProvider | F49: Desconstrução | G49: S23; S26; S29; S47 | H49: R06; R08; R25; R30 | I49: Worker HTTP Scrapling e política de destinos. | J49: Baixar página permitida e negar URL interna/redirect indevido em harness controlado. | K49: SL-S48-GATE | L49: Crítico | N49: =COUNTIFS(Tarefas!$D$2:$D$793,A49,Tarefas!$G$2:$G$793,"<>Gate",Tarefas!$X$2:$X$793,"OK") | O49: 10 | P49: =COUNTIFS(Tarefas!$D$2:$D$793,A49,Tarefas!$G$2:$G$793,"<>Gate",Tarefas!$X$2:$X$793,"DISPENSADO") | Q49: =IFERROR(N49/(O49-P49),0)
A50: S49 | B50: v0.9.0 | C50: Adicionar aquisição dinâmica com browser confinado | D50: Habilitar páginas dinâmicas sem transformar o app em um navegador irrestrito. | E50: Scrapling / browser | F50: Adaptação | G50: S24; S25; S26; S48 | H50: R01; R06; R08; R09; R25; R30 | I50: Browser worker lazy com política de rede e lifecycle. | J50: Renderizar SPA de fixture, capturar DOM e encerrar todos os processos após a tarefa. | K50: SL-S49-GATE | L50: Crítico | N50: =COUNTIFS(Tarefas!$D$2:$D$793,A50,Tarefas!$G$2:$G$793,"<>Gate",Tarefas!$X$2:$X$793,"OK") | O50: 10 | P50: =COUNTIFS(Tarefas!$D$2:$D$793,A50,Tarefas!$G$2:$G$793,"<>Gate",Tarefas!$X$2:$X$793,"DISPENSADO") | Q50: =IFERROR(N50/(O50-P50),0)
A51: S50 | B51: v0.9.0 | C51: Construir widget de pesquisa e snapshots | D51: Conectar descoberta à Mesa sem confundir página live, snapshot e síntese autoral. | E51: Whiteboard / pesquisa | F51: Próprio | G51: S19; S30; S47; S48; S49 | H51: R11; R14; R24; R25; R26; R31 | I51: Widget pesquisável, snapshots e promoção de resultados a células. | J51: Pesquisar, selecionar fontes, capturar, editar síntese e atualizar sem perda autoral. | K51: SL-S50-GATE | L51: Médio | N51: =COUNTIFS(Tarefas!$D$2:$D$793,A51,Tarefas!$G$2:$G$793,"<>Gate",Tarefas!$X$2:$X$793,"OK") | O51: 10 | P51: =COUNTIFS(Tarefas!$D$2:$D$793,A51,Tarefas!$G$2:$G$793,"<>Gate",Tarefas!$X$2:$X$793,"DISPENSADO") | Q51: =IFERROR(N51/(O51-P51),0)
A52: S51 | B52: v0.9.0 | C52: Integrar copiloto editorial e BYOK | D52: Gerar propostas de escrita contextualizadas sem conceder edição autônoma irrestrita. | E52: Copiloto / GenerationProvider | F52: Integração | G52: S21; S32; S46; S50 | H52: R08; R13; R23; R27; R31 | I52: Copiloto local/BYOK com diff, aceite e rollback. | J52: Solicitar revisão de parágrafo, comparar proposta e aceitar somente blocos selecionados. | K52: SL-S51-GATE | L52: Crítico | N52: =COUNTIFS(Tarefas!$D$2:$D$793,A52,Tarefas!$G$2:$G$793,"<>Gate",Tarefas!$X$2:$X$793,"OK") | O52: 10 | P52: =COUNTIFS(Tarefas!$D$2:$D$793,A52,Tarefas!$G$2:$G$793,"<>Gate",Tarefas!$X$2:$X$793,"DISPENSADO") | Q52: =IFERROR(N52/(O52-P52),0)
... A64: S63 | B64: v1.1.0 | C64: Atualizar motores com segurança e publicar v1.1 | D64: Provar que a composição pode ser mantida sem virar um fork monolítico congelado. | E64: Upstreams / estabilidade | F64: Integração | G64: S61; S62 | H64: R01; R30; R32; R33; R34 | I64: v1.1.0 e primeiro ciclo completo de manutenção upstream. | J64: Atualizar recorte necessário, comparar resultados e reverter se um contrato quebrar. | K64: SL-S63-GATE | L64: Crítico | N64: =COUNTIFS(Tarefas!$D$2:$D$793,A64,Tarefas!$G$2:$G$793,"<>Gate",Tarefas!$X$2:$X$793,"OK") | O64: 10 | P64: =COUNTIFS(Tarefas!$D$2:$D$793,A64,Tarefas!$G$2:$G$793,"<>Gate",Tarefas!$X$2:$X$793,"DISPENSADO") | Q64: =IFERROR(N64/(O64-P64),0)
A65: S64 | B65: v1.2.0 | C65: Escalar busca, ingestão e contexto com evidência | D65: Aumentar capacidade onde as medições mostram necessidade, sem reinventar motores. | E65: Escala / pipelines | F65: Evolução proposta | G65: S61; S63 | H65: R09; R12; R14; R21; R22; R36 | I65: Pipelines incrementais e budgets validados no corpus ampliado aprovado. | J65: Processar lote maior mantendo autoria responsiva e resultados/revisões corretos. | K65: SL-S64-GATE | L65: Alto | M65: Proposta de evolução: executar somente após ratificação ADR-017. Não adia correções de integridade/segurança pendentes. | N65: =COUNTIFS(Tarefas!$D$2:$D$793,A65,Tarefas!$G$2:$G$793,"<>Gate",Tarefas!$X$2:$X$793,"OK") | O65: 10 | P65: =COUNTIFS(Tarefas!$D$2:$D$793,A65,Tarefas!$G$2:$G$793,"<>Gate",Tarefas!$X$2:$X$793,"DISPENSADO") | Q65: =IFERROR(N65/(O65-P65),0)
A66: S65 | B66: v1.2.0 | C66: Consolidar pacotes offline e perfis portáveis | D66: Facilitar provisionamento sem rede e sem dependências técnicas instaladas pelo usuário. | E66: Distribuição offline / modelos | F66: Evolução proposta | G66: S32; S57; S63; S64 | H66: R01; R07; R09; R30; R36 | I66: Criador/importador de pacotes de capacidade e perfis por hardware. | J66: Levar pacote permitido para outra máquina compatível e usar IA local sem conectividade. | K66: SL-S65-GATE | L66: Crítico | M66: Proposta de evolução aprovada em ADR-017; não supõe que todas as licenças de pesos permitem redistribuição. | N66: =COUNTIFS(Tarefas!$D$2:$D$793,A66,Tarefas!$G$2:$G$793,"<>Gate",Tarefas!$X$2:$X$793,"OK") | O66: 10 | P66: =COUNTIFS(Tarefas!$D$2:$D$793,A66,Tarefas!$G$2:$G$793,"<>Gate",Tarefas!$X$2:$X$793,"DISPENSADO") | Q66: =IFERROR(N66/(O66-P66),0)
A67: S66 | B67: v1.2.0 | C67: Ampliar interoperabilidade e publicar v1.2 | D67: Preservar utilidade do conhecimento fora do Sandland e preparar contratos estáveis. | E67: Formatos abertos / exportação | F67: Evolução proposta | G67: S58; S63; S64; S65 | H67: R02; R04; R13; R29; R32; R36 | I67: v1.2.0 com interoperabilidade ampliada explicitamente aprovada. | J67: Exportar mesa/Peça e importar cópia sem perder os campos declarados suportados. | K67: SL-S66-GATE | L67: Alto | M67: Novos formatos/exportações dependem de aprovação em ADR-017. A versão do formato do Vault é independente da versão do app. | N67: =COUNTIFS(Tarefas!$D$2:$D$793,A67,Tarefas!$G$2:$G$793,"<>Gate",Tarefas!$X$2:$X$793,"OK") | O67: 10 | P67: =COUNTIFS(Tarefas!$D$2:$D$793,A67,Tarefas!$G$2:$G$793,"<>Gate",Tarefas!$X$2:$X$793,"DISPENSADO") | Q67: =IFERROR(N67/(O67-P67),0)
A68: S67 | B68: v2.0.0-beta.1 | C68: Ratificar desenho da v2.0 e contratos de provedores | D68: Abrir extensibilidade delimitada sem transformar o app em executor genérico de plugins. | E68: Arquitetura v2 / extensibilidade | F68: Evolução proposta | G68: S61; S66 | H68: R03; R06; R08; R32; R35 | I68: ADR v2.0, ameaça de extensão e superfície de SDK congelada. | J68: Provedor de exemplo tem capacidades explícitas e não acessa APIs internas do Core. | K68: SL-S67-GATE | L68: Crítico | M68: Proposta pós-v1: a v2.0 não exige colaboração em nuvem, marketplace, execução de scripts nas notas ou reescrita total dos motores. | N68: =COUNTIFS(Tarefas!$D$2:$D$793,A68,Tarefas!$G$2:$G$793,"<>Gate",Tarefas!$X$2:$X$793,"OK") | O68: 10 | P68: =COUNTIFS(Tarefas!$D$2:$D$793,A68,Tarefas!$G$2:$G$793,"<>Gate",Tarefas!$X$2:$X$793,"DISPENSADO") | Q68: =IFERROR(N68/(O68-P68),0)
A69: S68 | B69: v2.0.0-beta.1 | C69: Implementar SDK e kit de conformidade | D69: Tornar integrações reproduzíveis e verificáveis por contribuidores. | E69: Provider SDK / adapters | F69: Evolução proposta | G69: S67 | H69: R06; R08; R27; R32; R34; R35 | I69: SDK mínimo, mocks e harness de contratos. | J69: Criar provedor local de exemplo e testar comportamentos permitidos/negados sem chaves. | K69: SL-S68-GATE | L69: Crítico | N69: =COUNTIFS(Tarefas!$D$2:$D$793,A69,Tarefas!$G$2:$G$793,"<>Gate",Tarefas!$X$2:$X$793,"OK") | O69: 10 | P69: =COUNTIFS(Tarefas!$D$2:$D$793,A69,Tarefas!$G$2:$G$793,"<>Gate",Tarefas!$X$2:$X$793,"DISPENSADO") | Q69: =IFERROR(N69/(O69-P69),0)
A70: S69 | B70: v2.0.0-beta.1 | C70: Instalar extensões com permissões controladas | D70: Adicionar extensões sem perder soberania, segurança ou previsibilidade operacional. | E70: ExtensionHost / distribuição | F70: Evolução proposta | G70: S68 | H70: R06; R08; R09; R30; R33; R35 | I70: Instalação local/curada, revogação e lifecycle de extensões. | J70: Instalar provedor de exemplo, negar rede, revogar e remover sem tocar dados autorais. | K70: SL-S69-GATE | L70: Crítico | N70: =COUNTIFS(Tarefas!$D$2:$D$793,A70,Tarefas!$G$2:$G$793,"<>Gate",Tarefas!$X$2:$X$793,"OK") | O70: 10 | P70: =COUNTIFS(Tarefas!$D$2:$D$793,A70,Tarefas!$G$2:$G$793,"<>Gate",Tarefas!$X$2:$X$793,"DISPENSADO") | Q70: =IFERROR(N70/(O70-P70),0)
A71: S70 | B71: v2.0.0-beta.1 | C71: Atualizar recortes e consolidar beta v2.0 | D71: Consolidar arquitetura madura sem exigir reescrita do Vault ou perda de compatibilidade. | E71: Upstreams / SDK / formato | F71: Integração | G71: S68; S69 | H71: R01; R04; R22; R30; R32; R33; R35 | I71: v2.0.0-beta.1 com motores atualizados e adapters conformes. | J71: Executar o fluxo completo usando adapters sob SDK e manter dados v1.x intactos. | K71: SL-S70-GATE | L71: Crítico | N71: =COUNTIFS(Tarefas!$D$2:$D$793,A71,Tarefas!$G$2:$G$793,"<>Gate",Tarefas!$X$2:$X$793,"OK") | O71: 10 | P71: =COUNTIFS(Tarefas!$D$2:$D$793,A71,Tarefas!$G$2:$G$793,"<>Gate",Tarefas!$X$2:$X$793,"DISPENSADO") | Q71: =IFERROR(N71/(O71-P71),0)
A72: S71 | B72: v2.0.0-rc.1 | C72: Homologar compatibilidade e candidata v2.0 | D72: Comprovar que extensibilidade e evolução não romperam as promessas originais. | E72: Compatibilidade / RC v2 | F72: Próprio | G72: S70 | H72: R01; R02; R05; R06; R07; R09; R32; R35 | I72: v2.0.0-rc.1 e matriz de upgrade/rollback completa. | J72: Migrar cópias de Vaults v1.x, usar extensões e voltar/exportar sem perda autoral. | K72: SL-S71-GATE | L72: Crítico | N72: =COUNTIFS(Tarefas!$D$2:$D$793,A72,Tarefas!$G$2:$G$793,"<>Gate",Tarefas!$X$2:$X$793,"OK") | O72: 10 | P72: =COUNTIFS(Tarefas!$D$2:$D$793,A72,Tarefas!$G$2:$G$793,"<>Gate",Tarefas!$X$2:$X$793,"DISPENSADO") | Q72: =IFERROR(N72/(O72-P72),0)
A73: S72 | B73: v2.0.0 | C73: Publicar v2.0 e estabelecer continuidade | D73: Fechar o horizonte com produto completo, mantível e aberto, não com um fim artificial do software. | E73: Release / sustentabilidade | F73: Próprio | G73: S71 | H73: R01; R02; R05; R07; R30; R32; R33; R34; R35; R36 | I73: v2.0.0 estável, SDK documentado e processo contínuo de manutenção. | J73: Instalar stable, importar pesquisa, produzir Peça e verificar portabilidade/rollback de capacidades. | K73: SL-S72-GATE | L73: Crítico | N73: =COUNTIFS(Tarefas!$D$2:$D$793,A73,Tarefas!$G$2:$G$793,"<>Gate",Tarefas!$X$2:$X$793,"OK") | O73: 10 | P73: =COUNTIFS(Tarefas!$D$2:$D$793,A73,Tarefas!$G$2:$G$793,"<>Gate",Tarefas!$X$2:$X$793,"DISPENSADO") | Q73: =IFERROR(N73/(O73-P73),0)

Sheet Requisitos
A1: ID | B1: Área | C1: Requisito | D1: Origem | E1: Sprints planejados | F1: Verificação
A2: R01 | B2: Distribuição | C2: Linux x86_64/aarch64; Windows x86_64; macOS Apple Silicon/Intel | D2: RFC §§1,12,13 | E2: S01, S05, S06, S19, S24, S25, S26, S38, S39, S49, S56, S57, S59, S60, S63, S65, S70, S71, S72 | F2: Instalação limpa e matriz de capacidades por alvo; build cruzado não equivale a execução homologada.
A3: R02 | B3: Soberania | C3: Arquivos abertos são a autoridade; bancos e caches são reconstruíveis | D3: RFC §§1,2,4 | E3: S02, S07, S08, S10, S11, S13, S17, S21, S22, S30, S35, S37, S40, S41, S43, S53, S58, S60, S62, S66, S71, S72 | F3: Apagar caches preserva conteúdo, geometria, taxonomia, citações e histórico canônico.
A4: R03 | B4: Composição | C4: Núcleo Rust com motores gerenciados, condicionado à ADR | D4: Plano §1 | E4: S01, S03, S04, S06, S12, S23, S31, S42, S67 | F4: Alteração de Rust estrito aprovada; nenhum runtime é introduzido sem inventário e lifecycle.
A5: R04 | B5: Formato | C5: Markdown/frontmatter, IDs e extensões abertas documentadas | D5: RFC §§2,4,7 | E5: S02, S07, S10, S13, S14, S18, S20, S43, S66, S70 | F5: Round-trip sem perda semântica no perfil suportado; metadados desconhecidos preservados.
A6: R05 | B6: Durabilidade | C6: Journal/snapshots, recuperação e conflitos externos | D6: RFC §§4,11,13 | E6: S02, S07, S08, S10, S11, S14, S17, S21, S22, S23, S41, S54, S58, S60, S61, S62, S71, S72 | F6: Falhas em cada etapa não corrompem estado confirmado; janela de perda medida.
A7: R06 | B7: Segurança FS | C7: I/O por handles/capabilities e contenção por sistema operacional | D7: RFC §§1,4,8,13 | E7: S09, S11, S23, S24, S25, S26, S44, S48, S49, S54, S56, S57, S60, S67, S68, S69, S71 | F7: Tentativas de traversal, troca de links e fuga de processos são negadas nos perfis homologados.
A8: R07 | B8: Offline | C8: Autoria e leitura sem rede; inferência local após provisionamento | D8: RFC §1; conceito | E8: S01, S06, S07, S11, S15, S22, S31, S32, S34, S35, S46, S53, S59, S60, S65, S71, S72 | F8: Bloqueio de rede não impede trabalho local nem dispara fallback externo silencioso.
A9: R08 | B9: Privacidade | C9: Autorização de egress, segregação de segredos e escopos | D9: RFC §§1,8 | E9: S01, S06, S09, S23, S24, S25, S26, S29, S31, S32, S34, S44, S47, S48, S49, S51, S52, S54, S59, S62, S67, S68, S69 | F9: Nenhum envio sem política autorizada; ferramentas não podem ampliar seu próprio escopo.
A10: R09 | B10: Recursos | C10: Idle 350 MB, indexing leve 650 MB, inference 2,8 GB e unload 5 min | D10: RFC §§1,10,13 | E10: S05, S15, S19, S23, S24, S25, S26, S28, S31, S32, S36, S45, S49, S55, S56, S57, S60, S61, S64, S65, S69, S71 | F10: Medir árvore de processos e perfis aprovados; desvios bloqueiam release ou requerem revisão explícita.
A11: R10 | B11: Editor | C11: BlockSuite como motor de texto/blocos | D11: Escolha do autor; RFC §§5,7 | E11: S12, S13, S14, S15, S18, S20 | F11: Editor integrado ao Vault; Yjs não é a única cópia de conteúdo autoral.
A12: R11 | B12: Mesa | C12: PixiJS, células, grupos, arestas e múltiplos workspaces | D12: RFC §5 | E12: S02, S16, S17, S18, S19, S43, S50, S53 | F12: Topologia reaberta fielmente; conteúdo e ocorrência visual têm identidades separadas.
... A38: R37 | B38: Auditoria | C38: Rastreabilidade criptográfica com limites explícitos | D38: RFC §§1,11 | E38: S02, S08, S21, S58, S62 | F38: Encadeamento/checagem de eventos e limites de adulteração/ancoragem documentados.

Sheet ADRs
A1: ID | B1: Decisão | C1: Sprint | D1: Resultado esperado | E1: Estado | F1: Aprovador | G1: Evidência real
A2: ADR-001 | B2: Rust estrito versus núcleo Rust + workers | C2: S01 | D2: Aprovar composição poliglota controlada; se rejeitada, replanejar ports antes de avançar. | E2: A decidir | F2: Autor
A3: ADR-002 | B3: Autoridade JSON/journal e MPK derivado | C3: S02 | D3: Escolher precedência, fronteira de confirmação e formato aberto de histórico. | E3: A decidir | F3: Autor
A4: ADR-003 | B4: Licença do código próprio e recorte upstream | C4: S03 | D4: Ratificar licença; examinar por origem/arquivo, incluindo SearxNG e BlockSuite. | E4: A decidir | F4: Autor
A5: ADR-004 | B5: Política Jev, BYOK e modo offline | C5: S01 | D5: Jev de primeira classe quando autorizado; fallback local/pendência sem equivalente probabilístico presumido. | E5: A decidir | F5: Autor
A6: ADR-005 | B6: Perfil Markdown e representação de IDs | C6: S02 | D6: Fixar blocos suportados, campos preservados e extensões de proveniência. | E6: A decidir | F6: Autor
A7: ADR-006 | B7: OS de referência e matriz de distribuição | C7: S01 | D7: Escolher host principal sem reduzir os cinco alvos finais; obter acesso aos ambientes de teste. | E7: A decidir | F7: Autor
A8: ADR-007 | B8: Budgets e perfis de hardware | C8: S05 | D8: Fixar método de medição e perfis; OCR/STT pesado não recebe teto maior implicitamente. | E8: A decidir | F8: Autor
A9: ADR-008 | B9: Recorte BlockSuite e integração DOM/PixiJS | C9: S12 | D9: Fechar grafo de pacotes e licença/revisão; manter PixiJS como cena principal. | E9: A decidir | F9: Autor
A10: ADR-009 | B10: Protocolos de workers e políticas por SO | C10: S23 | D10: Fixar IPC, capabilities e fail-closed; tratar GPU/browser separadamente. | E10: A decidir | F10: Autor
A11: ADR-010 | B11: Runtime LocalAI e backends/modelos permitidos | C11: S31 | D11: Selecionar pacotes e desabilitar superfícies concorrentes de agentes/RAG/tools. | E11: A decidir | F11: Autor
A12: ADR-011 | B12: Modelos de resumo, embeddings e transcrição | C12: S32 | D12: Homologar por função/idioma/hardware; licença e hashes completos. | E12: A decidir | F12: Autor
A13: ADR-012 | B13: Taxonomia, thresholds e abstenção | C13: S35 | D13: Aprovar política calibrada; retirar merges silenciosos por distância/similaridade. | E13: A decidir | F13: Autor
... A19: ADR-018 | B19: SDK/extensões da v2.0 | C19: S67 | D19: Aprovar superfície restrita, distribuição e permissões; não abrir execução arbitrária de plugins. | E19: A decidir | F19: Autor

Sheet Motores
A1: Motor | B1: Trilha de sprints | C1: Modo de integração | D1: Recorte a reutilizar | E1: Excluir | F1: Desenvolvimento próprio | G1: Referência inicial
A2: BlockSuite | B2: S12–S15; S18; S20–S21; S63; S70 | C2: Bibliotecas + facade; patch set mínimo | D2: store/std/rich-text, modelos/blocos necessários; confirmar grafo workspace na revisão fixada | E2: UI AFFiNE, cloud e segundo canvas | F2: Codec Markdown, IDs, salvamento, overlay PixiJS e proveniência | G2: https://github.com/toeverything/AFFiNE/tree/canary/blocksuite
A3: PageIndex | B3: S42–S46; S63; S70 | C3: Recorte/fork delimitado + portas de modelo/dados | D3: page_index_md, navegação/resumos/tools úteis; confirmar módulos reais no checkout | E3: DocStore como autoridade, páginas de PDF artificiais, acesso global e cloud implícita | F3: Snapshot estrutural, IDs estáveis, relações cruzadas, budgets, invalidação e ToolBroker | G3: https://github.com/VectifyAI/PageIndex
A4: Qdrant | B4: S37–S38; S40–S41 se escolhido | C4: Spike; depois adapter sem extrair o storage interno | D4: Edge ou Server conforme capacidades testadas | E4: Segundo banco permanente se não for escolhido; UI/cluster sem necessidade | F4: SearchProvider, fusão/escopo, revisões e reconstrução | G4: https://qdrant.tech/documentation/edge/
A5: HelixDB | B5: S37; S39; S40–S41 se escolhido | C5: Spike; depois adapter embutido/local conforme evidência | D5: Engine/SDK e consultas requeridas de texto, vetores e relações derivadas | E5: Fonte da verdade e object storage remoto obrigatório | F5: SearchProvider, projeções da topologia e ciclo de índices | G5: https://docs.helix-db.com/database/helix-db/start-here/local-development/embedded-database
A6: Jev | B6: S34–S35; S52; S63 | C6: Adapter de serviço + contrato de decisões | D6: Choice, Score e Noul da API, com versão registrada | E6: Tentativa de extrair pesos fechados, executar Jev no LocalAI ou gerar texto livre | F6: Taxonomia, candidatos, calibração, consentimento, fallback e revisão | G6: https://docs.typesafe.ai/introduction
A7: Docling | B7: S27–S28; S30; S63; S70 | C7: Worker Python empacotado; adapter mínimo | D7: Parsing textual, tabelas, OCR aprovado e mapas de fonte | E7: Servidor sempre residente, todos os modelos e acesso amplo ao Vault | F7: NormalizedDocument, jobs, persistência, limites e reprocessamento | G7: https://github.com/docling-project/docling
A8: Readability / Turndown | B8: S29–S30; S48; S63; S70 | C8: Bibliotecas JS em ambiente DOM isolado | D8: Extração de artigo e conversão HTML para Markdown | E8: Scripts/trackers remotos e janela principal como parser hostil | F8: Sanitização, assets, origem, workers e normalização canônica | G8: https://github.com/mozilla/readability
A9: SearxNG | B9: S47; S50; S63; S70 | C9: Serviço local/pessoal configurado + adapter | D9: Metabusca e API JSON dos engines escolhidos | E9: Frontend próprio, instância pública implícita, alegação de busca offline | F9: Consulta/egress, UI, histórico, seleção, lifecycle e distribuição AGPL | G9: https://github.com/searxng/searxng
A10: Scrapling | B10: S48–S50; S63; S70 | C10: Worker HTTP e browser separado sob demanda | D10: Fetchers, parser/sessões e aquisição dinâmica quando aprovada | E10: Crawl irrestrito, um browser por widget e bypass universal prometido | F10: Política SSRF/rede, snapshots, pool, limits e promoção à Mesa | G10: https://github.com/D4Vinci/Scrapling
A11: LocalAI | B11: S31–S32; S36; S63; S65; S70 | C11: Runtime gerenciado, não reescrita de kernels | D11: APIs e backends homologados, carga/descarga e mecanismos de recursos | E11: Agentes, shell, memória/RAG paralelos e downloads automáticos arbitrários | F11: Catálogo, gateway, consentimento, pacotes, supervisor e diagnóstico | G11: https://github.com/mudler/LocalAI
A12: PixiJS / Tauri / SQLite | B12: S04–S11; S16–S19; S54–S57 | C12: Infraestrutura reutilizada com domínio próprio | D12: Janela/IPC, renderização e projeções SQL | E12: Autoridade de dados nas caches e permissões implícitas | F12: Vault, board, interação, conflitos, política de segurança e lifecycle | G12: Sandland-RFC-Integracao-e-Desconstrucao.md

Sheet Riscos
A1: ID | B1: Risco | C1: Severidade | D1: Onde | E1: Resposta / contingência
A2: K01 | B2: Incompatibilidade do requisito Rust estrito com os motores escolhidos | C2: Crítico | D2: S01 | E2: ADR-001 aprovada antes de implementar; rejeição implica replanejar ports, não fingir compatibilidade.
A3: K02 | B3: Perda autoral por dois stores ou dual-write arquivo/banco | C3: Crítico | D3: S02; S07–S11 | E3: Journal/checkpoints, escritor único, expected_revision e destruição de caches como gate.
A4: K03 | B4: BlockSuite não representa todo o perfil Markdown sem perda | C4: Alto | D4: S12–S15 | E4: Golden round-trip; limitar blocos ou extensão aberta; não converter silenciosamente em texto plano.
A5: K04 | B5: Recorte PageIndex reintroduz IDs instáveis ou acesso global | C5: Crítico | D5: S42–S46 | E5: Portas de dados/modelos, grafo canônico, corpus contrastivo e testes negativos por ferramenta.
A6: K05 | B6: Qdrant e HelixDB não satisfazem requisitos de distribuição/recuperação | C6: Alto | D6: S37–S40 | E6: Spikes comparáveis; decisão humana; se ambos falham, interromper integração e revisar ADR.
A7: K06 | B7: Jev obrigatório inviabiliza offline ou envia dados sem permissão | C7: Crítico | D7: S01; S34–S35 | E7: Integração nativa autorizada, fallback distinto/pendência e consentimento antes de qualquer chamada.
A8: K07 | B8: Parsers/browser expõem host a conteúdo malformado | C8: Crítico | D8: S23–S30; S48–S49 | E8: Perfis de SO reais, inputs mínimos, quotas, broker e capacidades desabilitadas onde não confinadas.
A9: K08 | B9: Sandbox de um SO é tratada como equivalente à de todos | C9: Crítico | D9: S24–S26; S56–S57 | E9: Testes nativos; matriz de capacidades; AppContainer/ACLs além de Jobs; macOS com mecanismo auditado.
A10: K09 | B10: LocalAI/OCR/browser impedem atingir budgets | C10: Alto | D10: S31–S32; S49; S55 | E10: Lazy start, unload, backpressure e medição de processos; revisão explícita, nunca esconder consumo.
A11: K10 | B11: Falta de hardware/assinatura/runner para cinco alvos | C11: Alto | D11: S01; S05; S56–S57 | E11: Inventariar acesso e custos; sem teste real não publicar plataforma como homologada.
A12: K11 | B12: Atualização upstream torna o fork difícil de manter | C12: Alto | D12: S03; S12; S42; S63; S70 | E12: Facades estreitas, patches pequenos, lockfiles e comparação diferencial.
... A19: K18 | B19: Migração ou purga apaga histórico necessário | C19: Crítico | D19: S08; S58; S62; S71 | E19: Preview, checkpoint, falhas injetadas, retenção explícita e restore testado.

Sheet Dependências
A1: Pré-requisito ID | B1: Item dependente ID | C1: Sprint origem | D1: Sprint destino | E1: Regra
A2: SL-S01-01 | B2: SL-S01-02 | C2: S01 | D2: S01 | E2: Bloqueia até aceite; sequência conservadora dentro do sprint
A3: SL-S01-02 | B3: SL-S01-03 | C3: S01 | D3: S01 | E3: Bloqueia até aceite; sequência conservadora dentro do sprint
A4: SL-S01-03 | B4: SL-S01-04 | C4: S01 | D4: S01 | E4: Bloqueia até aceite; sequência conservadora dentro do sprint
A5: SL-S01-04 | B5: SL-S01-05 | C5: S01 | D5: S01 | E5: Bloqueia até aceite; sequência conservadora dentro do sprint
A6: SL-S01-05 | B6: SL-S01-06 | C6: S01 | D6: S01 | E6: Bloqueia até aceite; sequência conservadora dentro do sprint
A7: SL-S01-06 | B7: SL-S01-07 | C7: S01 | D7: S01 | E7: Bloqueia até aceite; sequência conservadora dentro do sprint
A8: SL-S01-07 | B8: SL-S01-08 | C8: S01 | D8: S01 | E8: Bloqueia até aceite; sequência conservadora dentro do sprint
A9: SL-S01-08 | B9: SL-S01-09 | C9: S01 | D9: S01 | E9: Bloqueia até aceite; sequência conservadora dentro do sprint
A10: SL-S01-09 | B10: SL-S01-10 | C10: S01 | D10: S01 | E10: Bloqueia até aceite; sequência conservadora dentro do sprint
A11: SL-S01-01 | B11: SL-S01-GATE | C11: S01 | D11: S01 | E11: Bloqueia até aceite; sequência conservadora dentro do sprint
A12: SL-S01-02 | B12: SL-S01-GATE | C12: S01 | D12: S01 | E12: Bloqueia até aceite; sequência conservadora dentro do sprint
... A1547: SL-S72-10 | B1547: SL-S72-GATE | C1547: S72 | D1547: S72 | E1547: Bloqueia até aceite; sequência conservadora dentro do sprint

Sheet Gates
A1: Gate | B1: Sprint | C1: Versão | D1: Demonstração | E1: Entregável | F1: Evidência exigida | G1: Observação
A2: SL-S01-GATE | B2: S01 | C2: v0.0.1 | D2: Autor consegue explicar offline, Jev, workers e cinco alvos sem contradições. | E2: Escopo v1.0 e registro de decisões iniciais. | F2: reports/S01/acceptance.md
A3: SL-S02-GATE | B3: S02 | C3: v0.0.1 | D3: Fixtures independentes dos motores representam uma mesa e uma Peça completas. | E3: Schemas v0 do Vault, board, eventos, células e evidências. | F3: reports/S02/acceptance.md
A4: SL-S03-GATE | B4: S03 | C4: v0.0.1 | D4: Cada motor tem origem rastreável, fronteira proposta e decisão de manter/extrair/adaptar. | E4: Catálogo de componentes e política de manutenção upstream. | F4: reports/S03/acceptance.md
A5: SL-S04-GATE | B5: S04 | C5: v0.0.2 | D5: Um agente implementa uma tarefa isolada e o autor consegue revisar o patch e seus testes. | E5: Monorepo de trabalho e instruções de contribuição/agentes. | F5: reports/S04/acceptance.md
A6: SL-S05-GATE | B6: S05 | C6: v0.0.2 | D6: Falha introduzida em contrato bloqueia pipeline e um benchmark gera dados reproduzíveis. | E6: CI inicial, corpus licenciado e perfis mensuráveis. | F6: reports/S05/acceptance.md
A7: SL-S06-GATE | B7: S06 | C7: v0.0.2 | D7: Instalar build de desenvolvimento, navegar e selecionar um diretório sem rede. | E7: Shell Tauri com navegação Ingest/Mesa/Peça e IPC validado. | F7: reports/S06/acceptance.md
A8: SL-S07-GATE | B8: S07 | C8: v0.1.0 | D8: Criar Vault, salvar nota/asset, fechar e listar os mesmos IDs ao reabrir. | E8: VaultStore básico, manifest e armazenamento de assets por hash. | F8: reports/S07/acceptance.md
A9: SL-S08-GATE | B9: S08 | C9: v0.1.0 | D9: Interromper cada etapa de uma edição e recuperar o último estado confirmado. | E9: Journal durável e protocolo de publicação de revisões. | F9: reports/S08/acceptance.md
A10: SL-S09-GATE | B10: S09 | C10: v0.1.0 | D10: Solicitar um arquivo permitido e negar escapes durante resolução e concorrência. | E10: I/O autorizado por referências/handles e suíte de ataques de paths. | F10: reports/S09/acceptance.md
A11: SL-S10-GATE | B11: S10 | C11: v0.1.0 | D11: Editar/renomear fora do app, perder um evento de watcher e reconciliar sem perda. | E11: Reconciliação incremental e cache de inventário descartável. | F11: reports/S10/acceptance.md
A12: SL-S11-GATE | B12: S11 | C12: v0.1.0 | D12: Criar, modificar, corromper um cache, reconstruir e exportar um Vault local. | E12: v0.1.0 alpha técnica e utilitário de recuperação. | F12: reports/S11/acceptance.md
A13: SL-S12-GATE | B13: S12 | C13: v0.2.0 | D13: Editor mínimo funciona fora do monorepo de origem e sua origem/licença é rastreável. | E13: Pacote editorial isolado e ADR do recorte. | F13: reports/S12/acceptance.md
... A38: SL-S37-GATE | B38: S37 | C38: v0.7.0 | D38: Mesma fixture/consulta roda em providers fake e produz ranking/evidências verificáveis. | E38: Contrato de busca, indexação e protocolo comparativo. | F38: reports/S37/acceptance.md
A39: SL-S38-GATE | B39: S38 | C39: v0.7.0 | D39: Executar conformidade e benchmarks iguais ao candidato B, com conclusão viável/inviável. | E39: Relatório Qdrant e provider experimental. | F39: reports/S38/acceptance.md | G39: Este sprint fecha uma investigação, não aprova automaticamente Qdrant para produção. Conclusão negativa fundamentada é uma saída válida do spike.
A40: SL-S39-GATE | B40: S39 | C40: v0.7.0 | D40: Rodar o mesmo corpus e confrontar resultados com o candidato A. | E40: Relatório HelixDB e provider experimental. | F40: reports/S39/acceptance.md | G40: Concluir o spike não implica adotar HelixDB. Os dois protótipos ficam em experiments e não são distribuídos juntos por padrão.
A41: SL-S40-GATE | B41: S40 | C41: v0.7.0 | D41: Executar busca híbrida no app com apenas o backend escolhido instalado. | E41: SearchProvider de produção e ADR de seleção. | F41: reports/S40/acceptance.md
A42: SL-S41-GATE | B42: S41 | C42: v0.7.0 | D42: Editar/excluir material e verificar atualização da busca sem perder as fontes canônicas. | E42: v0.7.0 com busca híbrida e reconstrução assistida. | F42: reports/S41/acceptance.md
A43: SL-S42-GATE | B43: S42 | C43: v0.8.0 | D43: Construir índice de Markdown de fixture sem PDF e sem store canônico do SDK. | E43: Pacote experimental de contexto e ADR do recorte PageIndex. | F43: reports/S42/acceptance.md
A44: SL-S43-GATE | B44: S43 | C44: v0.8.0 | D44: Renomear notas, mover cartões e reconstruir mantendo IDs e referências. | E44: WorkspaceSnapshot e índice estrutural por revisão. | F44: reports/S43/acceptance.md
A45: SL-S44-GATE | B45: S44 | C45: v0.8.0 | D45: Modelo recebe ID fora do escopo e o broker nega mesmo com instrução em documento. | E45: Ferramentas de overview, grupo, célula, vizinhos e fonte. | F45: reports/S44/acceptance.md
A46: SL-S45-GATE | B46: S45 | C46: v0.8.0 | D46: Editar uma célula e recomputar apenas summaries dependentes, sem perder evidências. | E46: Skeleton Map com budget e cache incremental de resumos. | F46: reports/S45/acceptance.md
A47: SL-S46-GATE | B47: S46 | C47: v0.8.0 | D47: Perguntar sobre grupos que se contradizem e receber resposta apoiada nas revisões corretas. | E47: v0.8.0: consulta estrutural local sobre células e fontes. | F47: reports/S46/acceptance.md
A48: SL-S47-GATE | B48: S47 | C48: v0.9.0 | D48: Pesquisar por consulta autorizada e apresentar resultados sem enviar o board inteiro. | E48: Provider SearxNG com configuração, consentimento e testes de resposta. | F48: reports/S47/acceptance.md
A49: SL-S48-GATE | B49: S48 | C49: v0.9.0 | D49: Baixar página permitida e negar URL interna/redirect indevido em harness controlado. | E49: Worker HTTP Scrapling e política de destinos. | F49: reports/S48/acceptance.md
A50: SL-S49-GATE | B50: S49 | C50: v0.9.0 | D50: Renderizar SPA de fixture, capturar DOM e encerrar todos os processos após a tarefa. | E50: Browser worker lazy com política de rede e lifecycle. | F50: reports/S49/acceptance.md
A51: SL-S50-GATE | B51: S50 | C51: v0.9.0 | D51: Pesquisar, selecionar fontes, capturar, editar síntese e atualizar sem perda autoral. | E51: Widget pesquisável, snapshots e promoção de resultados a células. | F51: reports/S50/acceptance.md
A52: SL-S51-GATE | B52: S51 | C52: v0.9.0 | D52: Solicitar revisão de parágrafo, comparar proposta e aceitar somente blocos selecionados. | E52: Copiloto local/BYOK com diff, aceite e rollback. | F52: reports/S51/acceptance.md
... A64: SL-S63-GATE | B64: S63 | C64: v1.1.0 | D64: Atualizar recorte necessário, comparar resultados e reverter se um contrato quebrar. | E64: v1.1.0 e primeiro ciclo completo de manutenção upstream. | F64: reports/S63/acceptance.md
A65: SL-S64-GATE | B65: S64 | C65: v1.2.0 | D65: Processar lote maior mantendo autoria responsiva e resultados/revisões corretos. | E65: Pipelines incrementais e budgets validados no corpus ampliado aprovado. | F65: reports/S64/acceptance.md | G65: Proposta de evolução: executar somente após ratificação ADR-017. Não adia correções de integridade/segurança pendentes.
A66: SL-S65-GATE | B66: S65 | C66: v1.2.0 | D66: Levar pacote permitido para outra máquina compatível e usar IA local sem conectividade. | E66: Criador/importador de pacotes de capacidade e perfis por hardware. | F66: reports/S65/acceptance.md | G66: Proposta de evolução aprovada em ADR-017; não supõe que todas as licenças de pesos permitem redistribuição.
A67: SL-S66-GATE | B67: S66 | C67: v1.2.0 | D67: Exportar mesa/Peça e importar cópia sem perder os campos declarados suportados. | E67: v1.2.0 com interoperabilidade ampliada explicitamente aprovada. | F67: reports/S66/acceptance.md | G67: Novos formatos/exportações dependem de aprovação em ADR-017. A versão do formato do Vault é independente da versão do app.
A68: SL-S67-GATE | B68: S67 | C68: v2.0.0-beta.1 | D68: Provedor de exemplo tem capacidades explícitas e não acessa APIs internas do Core. | E68: ADR v2.0, ameaça de extensão e superfície de SDK congelada. | F68: reports/S67/acceptance.md | G68: Proposta pós-v1: a v2.0 não exige colaboração em nuvem, marketplace, execução de scripts nas notas ou reescrita total dos motores.
A69: SL-S68-GATE | B69: S68 | C69: v2.0.0-beta.1 | D69: Criar provedor local de exemplo e testar comportamentos permitidos/negados sem chaves. | E69: SDK mínimo, mocks e harness de contratos. | F69: reports/S68/acceptance.md
A70: SL-S69-GATE | B70: S69 | C70: v2.0.0-beta.1 | D70: Instalar provedor de exemplo, negar rede, revogar e remover sem tocar dados autorais. | E70: Instalação local/curada, revogação e lifecycle de extensões. | F70: reports/S69/acceptance.md
A71: SL-S70-GATE | B71: S70 | C71: v2.0.0-beta.1 | D71: Executar o fluxo completo usando adapters sob SDK e manter dados v1.x intactos. | E71: v2.0.0-beta.1 com motores atualizados e adapters conformes. | F71: reports/S70/acceptance.md
A72: SL-S71-GATE | B72: S71 | C72: v2.0.0-rc.1 | D72: Migrar cópias de Vaults v1.x, usar extensões e voltar/exportar sem perda autoral. | E72: v2.0.0-rc.1 e matriz de upgrade/rollback completa. | F72: reports/S71/acceptance.md
A73: SL-S72-GATE | B73: S72 | C73: v2.0.0 | D73: Instalar stable, importar pesquisa, produzir Peça e verificar portabilidade/rollback de capacidades. | E73: v2.0.0 estável, SDK documentado e processo contínuo de manutenção. | F73: reports/S72/acceptance.md
